Workbook

Sheet Summary_Dashboard
A1: INSURANCE CLAIMS — ANALYSIS DASHBOARD
A2: Data: 3,000-claim sample | Tejas Surana | Portfolio piece for Data & Business Analyst role
A4: Total Claims Analyzed | C4: Total Fraud Claims | E4: Overall Fraud Rate | G4: Total Claim Amount ($)
A5: =COUNTA(Cleaned_Data!$A$5:$A$3004) -> 3000 | C5: =COUNTIFS(Cleaned_Data!$O$5:$O$3004,1) -> 167 | E5: =COUNTIFS(Cleaned_Data!$O$5:$O$3004,1)/COUNTA(Cleaned_Data!$A$5:$A$3004) -> 0.055666667 | G5: =SUM(Cleaned_Data!$E$5:$E$3004) -> 49461800
A7: Avg Claim Amount ($) | C7: Highest-Risk Category (Motor) | E7: Fraud Claims > $20,000 | G7: Distinct States Covered
A8: =AVERAGE(Cleaned_Data!$E$5:$E$3004) -> 16487.267 | C8: =COUNTIFS(Cleaned_Data!$C$5:$C$3004,"Motor",Cleaned_Data!$O$5:$O$3004,1)/COUNTIFS(Cleaned_Data!$C$5:$C$3004,"Motor") -> 0.063559322 | E8: =COUNTIFS(Cleaned_Data!$E$5:$E$3004,">20000",Cleaned_Data!$O$5:$O$3004,1) -> 37 | G8: =SUMPRODUCT((Cleaned_Data!$F$5:$F$3004<>"")/COUNTIF(Cleaned_Data!$F$5:$F$3004,Cleaned_Data!$F$5:$F$3004&"")) -> 16
A10: Fraud Rate by Insurance Type
A11: Insurance Type | B11: Fraud Rate %
A12: =Pivot_Analysis!A6 -> Health | B12: =Pivot_Analysis!D6 -> 0.066132265
A13: =Pivot_Analysis!A7 -> Life | B13: =Pivot_Analysis!D7 -> 0.044176707
A14: =Pivot_Analysis!A8 -> Mobile | B14: =Pivot_Analysis!D8 -> 0.054924242
A15: =Pivot_Analysis!A9 -> Motor | B15: =Pivot_Analysis!D9 -> 0.063559322
A16: =Pivot_Analysis!A10 -> Property | B16: =Pivot_Analysis!D10 -> 0.051282051
A17: =Pivot_Analysis!A11 -> Travel | B17: =Pivot_Analysis!D11 -> 0.054435484

Sheet Raw_Claims_Data
A1: RAW DATA — Insurance Claims (3,000-record sample, unedited source)
A3: TRANSACTION_ID | B3: CUSTOMER_NAME | C3: INSURANCE_TYPE | D3: PREMIUM_AMOUNT | E3: CLAIM_AMOUNT | F3: STATE | G3: CLAIM_STATUS | H3: INCIDENT_SEVERITY | I3: AUTHORITY_CONTACTED | J3: INCIDENT_CITY | K3: INCIDENT_STATE | L3: INCIDENT_HOUR_OF_THE_DAY | M3: VENDOR_ID | N3: AGENT_ID
A4: TXN00000001 | B4: Christopher Demarest | C4: Health | D4: 157.13 | E4: 9000 | F4: AZ | G4: A | H4: Major Loss | I4: Police | J4: Savannah | K4: GA | L4: 4 | M4: VNDR00556 | N4: AGENT00413
A5: TXN00000002 | B5: Ricardo Gatlin | C5: Property | D5: 141.71 | E5: 26000 | F5: CO | G5: A | H5: Total Loss | I5: Ambulance | J5: Montgomery | K5: AL | L5: 0 | M5: VNDR00592 | N5: AGENT00769
A6: TXN00000003 | B6: Lashawn Engles | C6: Property | D6: 157.24 | E6: 13000 | F6: CA | G6: A | H6: Total Loss | I6: Police | J6: Grand Junction | K6: CO | L6: 19 | M6: VNDR00031 | N6: AGENT00883
A7: TXN00000004 | B7: Steven Bassett | C7: Health | D7: 172.87 | E7: 16000 | F7: GA | G7: A | H7: Minor Loss | I7: Ambulance | J7: Savannah | K7: GA | L7: 12 | M7: VNDR00075 | N7: AGENT00278
A8: TXN00000005 | B8: Jason Rodriguez | C8: Travel | D8: 88.53 | E8: 3000 | F8: CA | G8: A | H8: Major Loss | I8: Police | J8: Nashville | K8: TN | L8: 18 | M8: VNDR00472 | N8: AGENT00636
A9: TXN00000006 | B9: Terrance Han | C9: Life | D9: 87.02 | E9: 63000 | F9: AZ | G9: A | H9: Major Loss | I9: Ambulance | J9: Glendale | K9: AZ | L9: 0 | N9: AGENT00402
A10: TXN00000007 | B10: Dennis Johnson | C10: Health | D10: 197.23 | E10: 3000 | F10: FL | G10: A | H10: Major Loss | I10: Police | J10: Manchester | K10: CT | L10: 10 | M10: VNDR00150 | N10: AGENT00322
A11: TXN00000008 | B11: Maryalice Martinez | C11: Motor | D11: 83.77 | E11: 8000 | F11: GA | G11: A | H11: Total Loss | I11: Police | J11: Panama City Beach | K11: FL | L11: 10 | M11: VNDR00326 | N11: AGENT00152
A12: TXN00000009 | B12: Nicholas Hamilton | C12: Motor | D12: 82.14 | E12: 5000 | F12: KY | G12: A | H12: Major Loss | I12: Police | J12: Glendale | K12: AZ | L12: 22 | M12: VNDR00437 | N12: AGENT00450
A13: TXN00000010 | B13: Nicholas Honokaupu | C13: Travel | D13: 71.29 | E13: 4000 | F13: AL | G13: A | H13: Major Loss | J13: San Leandro | K13: CA | L13: 4 | N13: AGENT00682
A14: TXN00000011 | B14: Janet Watts | C14: Life | D14: 61.45 | E14: 92000 | F14: CT | G14: A | H14: Major Loss | I14: Ambulance | J14: Crofton | K14: MD | L14: 23 | M14: VNDR00163 | N14: AGENT01091
A15: TXN00000012 | B15: Patricia Garrett | C15: Motor | D15: 101.15 | E15: 8000 | F15: TN | G15: D | H15: Major Loss | I15: Ambulance | J15: Manchester | K15: CT | L15: 3 | N15: AGENT00288
A16: TXN00000013 | B16: Lisa Rosario | C16: Health | D16: 157.95 | E16: 11000 | F16: AK | G16: A | H16: Major Loss | J16: Louisville | K16: KY | L16: 22 | M16: VNDR00191 | N16: AGENT00015
A17: TXN00000014 | B17: Felicita Stoughton | C17: Life | D17: 64.16 | E17: 51000 | F17: GA | G17: A | H17: Total Loss | I17: Ambulance | J17: Anchorage | K17: AK | L17: 0 | N17: AGENT01094
A18: TXN00000015 | B18: David Pennington | C18: Mobile | D18: 6.76 | E18: 700 | F18: AR | G18: A | H18: Major Loss | I18: Police | J18: Arvada | K18: CO | L18: 11 | M18: VNDR00135 | N18: AGENT00324
A19: TXN00000016 | B19: William Halcomb | C19: Motor | D19: 128.73 | E19: 9000 | F19: DC | G19: A | H19: Minor Loss | I19: Police | J19: Fayetteville | K19: AR | L19: 22 | M19: VNDR00051 | N19: AGENT00608
A20: TXN00000017 | B20: Michael Kimball | C20: Property | D20: 114.42 | E20: 39000 | F20: CT | G20: A | H20: Major Loss | I20: Other | J20: Washington | K20: DC | L20: 2 | M20: VNDR00238 | N20: AGENT00911
A21: TXN00000018 | B21: Mark Huang | C21: Property | D21: 157.18 | E21: 40000 | F21: CO | G21: A | H21: Major Loss | I21: Police | J21: Montgomery | K21: AL | L21: 14 | N21: AGENT00079
A22: TXN00000019 | B22: Marshall Worm | C22: Motor | D22: 116.55 | E22: 8000 | F22: CT | G22: A | H22: Total Loss | I22: Ambulance | J22: Fitchburg | K22: MA | L22: 20 | M22: VNDR00107 | N22: AGENT00994
A23: TXN00000020 | B23: Mary Carmona | C23: Life | D23: 77.17 | E23: 68000 | F23: DC | G23: A | H23: Total Loss | J23: Arvada | K23: CO | L23: 1 | N23: AGENT00490
A24: TXN00000021 | B24: Stacey Lopez | C24: Health | D24: 155.23 | E24: 17000 | F24: VT | G24: A | H24: Total Loss | I24: Other | J24: Arvada | K24: CO | L24: 3 | M24: VNDR00215 | N24: AGENT00446
A25: TXN00000022 | B25: David Goodman | C25: Mobile | D25: 9.15 | E25: 300 | F25: CA | G25: A | H25: Major Loss | I25: Ambulance | J25: Washington | K25: DC | L25: 18 | N25: AGENT00379
A26: TXN00000023 | B26: Doris Yazzie | C26: Life | D26: 81.45 | E26: 80000 | F26: FL | G26: A | H26: Major Loss | I26: Ambulance | J26: Woodland | K26: CA | L26: 7 | M26: VNDR00375 | N26: AGENT00302
A27: TXN00000024 | B27: Matt Mattis | C27: Property | D27: 153.04 | E27: 10000 | F27: AK | G27: A | H27: Total Loss | J27: Arvada | K27: CO | L27: 22 | M27: VNDR00585 | N27: AGENT00266
A28: TXN00000025 | B28: Roberto Trudel | C28: Property | D28: 120.31 | E28: 30000 | F28: GA | G28: A | H28: Minor Loss | I28: Police | J28: Lynn Haven | K28: FL | L28: 10 | N28: AGENT00947
A29: TXN00000026 | B29: Brian Conley | C29: Property | D29: 87.09 | E29: 37000 | F29: MD | G29: A | H29: Minor Loss | I29: Police | J29: Nashville | K29: TN | L29: 13 | M29: VNDR00051 | N29: AGENT00070
A30: TXN00000027 | B30: Barbara Clouthier | C30: Health | D30: 130.78 | E30: 17000 | F30: CA | G30: A | H30: Total Loss | I30: Police | J30: Savannah | K30: GA | L30: 11 | N30: AGENT00739
A31: TXN00000028 | B31: Elbert Felix | C31: Health | D31: 119.4 | E31: 19000 | F31: AR | G31: A | H31: Minor Loss | I31: Police | J31: Quincy | K31: MA | L31: 0 | M31: VNDR00310 | N31: AGENT01169
A32: TXN00000029 | B32: Ronald Shaver | C32: Property | D32: 159.2 | E32: 37000 | F32: AL | G32: A | H32: Minor Loss | J32: Pasadena | K32: MD | L32: 7 | M32: VNDR00339 | N32: AGENT00431
A33: TXN00000030 | B33: Lauren Loftin | C33: Mobile | D33: 8.32 | E33: 600 | F33: TN | G33: A | H33: Major Loss | I33: Police | J33: Arvada | K33: CO | L33: 19 | M33: VNDR00233 | N33: AGENT00546
A34: TXN00000031 | B34: Mildred Whitten | C34: Health | D34: 147.7 | E34: 13000 | F34: AZ | G34: A | H34: Major Loss | I34: Ambulance | J34: Arvada | K34: CO | L34: 3 | M34: VNDR00249 | N34: AGENT00531
A35: TXN00000032 | B35: Alyssa Bowen | C35: Property | D35: 124.45 | E35: 15000 | F35: MD | G35: A | H35: Minor Loss | I35: Ambulance | J35: Montgomery | K35: AL | L35: 22 | N35: AGENT01134
A36: TXN00000033 | B36: James Hendrickson | C36: Life | D36: 51.18 | E36: 27000 | F36: DC | G36: A | H36: Minor Loss | I36: Police | J36: Louisville | K36: KY | L36: 0 | N36: AGENT00552
A37: TXN00000034 | B37: Brent Lusk | C37: Mobile | D37: 8.38 | E37: 100 | F37: MA | G37: A | H37: Minor Loss | I37: Other | J37: Manchester | K37: CT | L37: 17 | M37: VNDR00045 | N37: AGENT00623
A38: TXN00000035 | B38: Charles Johnson | C38: Life | D38: 95.16 | E38: 74000 | F38: CA | G38: A | H38: Major Loss | J38: Louisville | K38: KY | L38: 13 | M38: VNDR00226 | N38: AGENT00313
A39: TXN00000036 | B39: Gloria Davis | C39: Life | D39: 66.73 | E39: 69000 | F39: CO | G39: A | H39: Minor Loss | I39: Ambulance | J39: Pasadena | K39: MD | L39: 7 | N39: AGENT00886
A40: TXN00000037 | B40: Irene Metcalf | C40: Mobile | D40: 8.27 | E40: 300 | F40: FL | G40: A | H40: Minor Loss | I40: Police | J40: Panama City | K40: FL | L40: 8 | N40: AGENT00690
A41: TXN00000038 | B41: Patsy Cantu | C41: Life | D41: 50.3 | E41: 18000 | F41: CA | G41: A | H41: Total Loss | I41: Police | J41: Montgomery | K41: AL | L41: 14 | N41: AGENT00678
A42: TXN00000039 | B42: Louis Yang | C42: Mobile | D42: 6.59 | E42: 600 | F42: KY | G42: A | H42: Minor Loss | I42: Ambulance | J42: Washington | K42: DC | L42: 6 | M42: VNDR00560 | N42: AGENT00132
A43: TXN00000040 | B43: Albert Wilkie | C43: Mobile | D43: 11.04 | E43: 600 | F43: MA | G43: A | H43: Total Loss | I43: Other | J43: Manchester | K43: CT | L43: 0 | N43: AGENT00284
A44: TXN00000041 | B44: Paula Davis | C44: Life | D44: 86.77 | E44: 34000 | F44: DC | G44: A | H44: Major Loss | I44: Ambulance | J44: Manchester | K44: CT | L44: 2 | M44: VNDR00018 | N44: AGENT00312
A45: TXN00000042 | B45: Dorothy James | C45: Motor | D45: 89.11 | E45: 2000 | F45: VT | G45: A | H45: Minor Loss | I45: Police | J45: Anchorage | K45: AK | L45: 14 | M45: VNDR00560 | N45: AGENT00622
A46: TXN00000043 | B46: Wayne Landrum | C46: Property | D46: 140.72 | E46: 35000 | F46: CT | G46: A | H46: Total Loss | I46: Police | J46: Farmington | K46: AR | L46: 0 | M46: VNDR00086 | N46: AGENT00896
A47: TXN00000044 | B47: Edward Igtanloc | C47: Property | D47: 129.9 | E47: 18000 | F47: FL | G47: A | H47: Minor Loss | I47: Ambulance | J47: Oklahoma City | K47: OK | L47: 18 | N47: AGENT00744
A48: TXN00000045 | B48: Cheryl Silva | C48: Life | D48: 84.99 | E48: 66000 | F48: AL | G48: A | H48: Minor Loss | I48: Ambulance | J48: Montgomery | K48: AL | L48: 16 | N48: AGENT00617
A49: TXN00000046 | B49: Mary Cotton | C49: Travel | D49: 90.04 | E49: 5000 | F49: AZ | G49: A | H49: Minor Loss | J49: Farmington | K49: AR | L49: 5 | M49: VNDR00071 | N49: AGENT00969
A50: TXN00000047 | B50: Harold Garcia | C50: Motor | D50: 117.72 | E50: 7000 | F50: CA | G50: D | H50: Major Loss | I50: Police | J50: Arvada | K50: CO | L50: 0 | N50: AGENT00642
A51: TXN00000048 | B51: Tori Mcbride | C51: Property | D51: 109.74 | E51: 15000 | F51: VT | G51: D | H51: Minor Loss | J51: Richmond | K51: VT | L51: 2 | M51: VNDR00009 | N51: AGENT00845
A52: TXN00000049 | B52: Bertha Roseman | C52: Mobile | D52: 9.05 | E52: 300 | F52: KY | G52: A | H52: Major Loss | I52: Ambulance | J52: Washington | K52: DC | L52: 22 | N52: AGENT00580
A53: TXN00000050 | B53: Travis Louis | C53: Motor | D53: 116.99 | E53: 10000 | F53: AZ | G53: A | H53: Minor Loss | I53: Ambulance | J53: Glendale | K53: AZ | L53: 13 | M53: VNDR00488 | N53: AGENT00697
A54: TXN00000051 | B54: Marion Dollyhigh | C54: Mobile | D54: 11.04 | E54: 400 | F54: KY | G54: A | H54: Total Loss | I54: Ambulance | J54: Greensboro | K54: VT | L54: 22 | N54: AGENT00780
A55: TXN00000052 | B55: Thomas Lancon | C55: Mobile | D55: 6.63 | E55: 600 | F55: VT | G55: A | H55: Total Loss | I55: Other | J55: Montgomery | K55: AL | L55: 22 | M55: VNDR00277 | N55: AGENT01183
A56: TXN00000053 | B56: Wanda Ellison | C56: Motor | D56: 82.82 | E56: 9000 | F56: OK | G56: A | H56: Major Loss | I56: Ambulance | J56: Anchorage | K56: AK | L56: 21 | M56: VNDR00025 | N56: AGENT00293
A57: TXN00000054 | B57: Donald Meehan | C57: Property | D57: 104.05 | E57: 16000 | F57: OK | G57: A | H57: Minor Loss | I57: Ambulance | J57: Savannah | K57: GA | L57: 5 | M57: VNDR00448 | N57: AGENT01049
A58: TXN00000055 | B58: Phillip Walker | C58: Property | D58: 137.02 | E58: 19000 | F58: AL | G58: A | H58: Total Loss | I58: Ambulance | J58: Glen Burnie | K58: MD | L58: 9 | M58: VNDR00445 | N58: AGENT00046
A59: TXN00000056 | B59: Claire Carter | C59: Travel | D59: 75.99 | E59: 3000 | F59: VT | G59: A | H59: Total Loss | I59: Ambulance | J59: Waltham | K59: MA | L59: 19 | M59: VNDR00498 | N59: AGENT00224
A60: TXN00000057 | B60: Antony Ender | C60: Motor | D60: 92.71 | E60: 2000 | F60: MD | G60: A | H60: Total Loss | I60: Police | J60: Jackson | K60: CA | L60: 7 | M60: VNDR00358 | N60: AGENT00410
A61: TXN00000058 | B61: John Tilley | C61: Property | D61: 111.33 | E61: 30000 | F61: AR | G61: A | H61: Total Loss | I61: Ambulance | J61: Anchorage | K61: AK | L61: 14 | M61: VNDR00164 | N61: AGENT00515
A62: TXN00000059 | B62: John Flores | C62: Mobile | D62: 8.51 | E62: 300 | F62: VT | G62: A | H62: Major Loss | I62: Ambulance | J62: Oklahoma City | K62: OK | L62: 21 | M62: VNDR00083 | N62: AGENT00824
A63: TXN00000060 | B63: Edward Laderman | C63: Travel | D63: 97.08 | E63: 2000 | F63: GA | G63: A | H63: Total Loss | J63: Louisville | K63: KY | L63: 11 | N63: AGENT00288
A64: TXN00000061 | B64: Margaret Bolen | C64: Property | D64: 155.05 | E64: 16000 | F64: AL | G64: A | H64: Minor Loss | I64: Ambulance | J64: Fairfax | K64: VT | L64: 15 | M64: VNDR00457 | N64: AGENT00308
A65: TXN00000062 | B65: Calvin Eichelberger | C65: Property | D65: 124.97 | E65: 35000 | F65: DC | G65: A | H65: Total Loss | I65: Other | J65: Oklahoma City | K65: OK | L65: 21 | M65: VNDR00383 | N65: AGENT01028
A66: TXN00000063 | B66: Arthur Mitchell | C66: Property | D66: 151.81 | E66: 15000 | F66: FL | G66: A | H66: Minor Loss | I66: Ambulance | J66: Glendale | K66: AZ | L66: 20 | M66: VNDR00010 | N66: AGENT00111
A67: TXN00000064 | B67: Debra Oliphant | C67: Property | D67: 121.54 | E67: 31000 | F67: TN | G67: A | H67: Major Loss | I67: Police | J67: Annapolis | K67: MD | L67: 22 | M67: VNDR00269 | N67: AGENT00697
A68: TXN00000065 | B68: Mariann Hill | C68: Travel | D68: 77.47 | E68: 3000 | F68: CA | G68: D | H68: Total Loss | I68: Ambulance | J68: Millersville | K68: MD | L68: 12 | M68: VNDR00314 | N68: AGENT00018
A69: TXN00000066 | B69: Michael Beltrami | C69: Life | D69: 67.55 | E69: 96000 | F69: VT | G69: A | H69: Major Loss | I69: Police | J69: Manchester | K69: CT | L69: 13 | N69: AGENT00612
A70: TXN00000067 | B70: Marion Coffey | C70: Travel | D70: 98.49 | E70: 2000 | F70: MD | G70: A | H70: Total Loss | I70: Other | J70: Anchorage | K70: AK | L70: 5 | M70: VNDR00383 | N70: AGENT00141
A71: TXN00000068 | B71: Denise Blake | C71: Mobile | D71: 11.21 | E71: 400 | F71: KY | G71: A | H71: Total Loss | I71: Other | J71: Manchester | K71: CT | L71: 10 | N71: AGENT00572
A72: TXN00000069 | B72: William Martin | C72: Health | D72: 156.2 | E72: 3000 | F72: TN | G72: A | H72: Total Loss | I72: Police | J72: Oakland | K72: CA | L72: 7 | M72: VNDR00239 | N72: AGENT00565
A73: TXN00000070 | B73: Jacqueline Simpson | C73: Mobile | D73: 7.23 | E73: 100 | F73: OK | G73: A | H73: Major Loss | I73: Other | J73: Fayetteville | K73: AR | L73: 9 | N73: AGENT00603
A74: TXN00000071 | B74: James Thurgood | C74: Mobile | D74: 11.63 | E74: 400 | F74: MD | G74: A | H74: Total Loss | I74: Ambulance | J74: Anchorage | K74: AK | L74: 1 | M74: VNDR00033 | N74: AGENT01107
A75: TXN00000072 | B75: Mathew Sims | C75: Travel | D75: 74.36 | E75: 5000 | F75: GA | G75: A | H75: Total Loss | I75: Police | J75: Arvada | K75: CO | L75: 5 | M75: VNDR00407 | N75: AGENT00615
A76: TXN00000073 | B76: Jeremy Riccio | C76: Life | D76: 76.97 | E76: 99000 | F76: AR | G76: A | H76: Minor Loss | I76: Ambulance | J76: Panama City Beach | K76: FL | L76: 3 | N76: AGENT00309
A77: TXN00000074 | B77: Susan Petersen | C77: Mobile | D77: 6.15 | E77: 300 | F77: CO | G77: A | H77: Total Loss | I77: Ambulance | J77: Montgomery | K77: AL | L77: 9 | M77: VNDR00056 | N77: AGENT00315
A78: TXN00000075 | B78: Anthony Girard | C78: Life | D78: 78.34 | E78: 52000 | F78: TN | G78: A | H78: Minor Loss | I78: Ambulance | J78: Telluride | K78: CO | L78: 17 | N78: AGENT00561
A79: TXN00000076 | B79: Eileen Svoboda | C79: Life | D79: 67.88 | E79: 59000 | F79: GA | G79: A | H79: Major Loss | I79: Ambulance | J79: Wheat Ridge | K79: CO | L79: 19 | M79: VNDR00521 | N79: AGENT00935
A80: TXN00000077 | B80: William Zeigler | C80: Life | D80: 68.72 | E80: 60000 | F80: TN | G80: A | H80: Major Loss | J80: Livermore | K80: CA | L80: 5 | M80: VNDR00488 | N80: AGENT00210
A81: TXN00000078 | B81: James Hodges | C81: Life | D81: 86.31 | E81: 39000 | F81: CA | G81: A | H81: Major Loss | I81: Ambulance | J81: Fayetteville | K81: AR | L81: 17 | N81: AGENT00283
A82: TXN00000079 | B82: Carlos Montello | C82: Motor | D82: 100.14 | E82: 7000 | F82: MA | G82: A | H82: Major Loss | I82: Police | J82: Oakland | K82: CA | L82: 15 | N82: AGENT00094
A83: TXN00000080 | B83: Gary Enciso | C83: Travel | D83: 81.79 | E83: 4000 | F83: CO | G83: A | H83: Major Loss | I83: Ambulance | J83: Fayetteville | K83: AR | L83: 4 | N83: AGENT00680
A84: TXN00000081 | B84: Melva Ramirez | C84: Life | D84: 88.05 | E84: 79000 | F84: OK | G84: A | H84: Minor Loss | I84: Ambulance | J84: Savannah | K84: GA | L84: 21 | N84: AGENT00319
A85: TXN00000082 | B85: Richard Lavalle | C85: Travel | D85: 89.36 | E85: 2000 | F85: CT | G85: A | H85: Major Loss | I85: Ambulance | J85: Savannah | K85: GA | L85: 10 | M85: VNDR00287 | N85: AGENT00630
A86: TXN00000083 | B86: Marion Talley | C86: Life | D86: 95.04 | E86: 14000 | F86: MD | G86: A | H86: Minor Loss | I86: Ambulance | J86: Anchorage | K86: AK | L86: 10 | M86: VNDR00466 | N86: AGENT00559
A87: TXN00000084 | B87: Diane Givens | C87: Mobile | D87: 11.57 | E87: 100 | F87: TN | G87: A | H87: Minor Loss | J87: Panama City | K87: FL | L87: 13 | N87: AGENT00771
A88: TXN00000085 | B88: Jimmie Herbert | C88: Motor | D88: 109.33 | E88: 6000 | F88: AR | G88: A | H88: Total Loss | J88: Youngstown | K88: FL | L88: 0 | M88: VNDR00077 | N88: AGENT00304
A89: TXN00000086 | B89: James Miles | C89: Motor | D89: 126.63 | E89: 1000 | F89: TN | G89: A | H89: Major Loss | I89: Police | J89: Arvada | K89: CO | L89: 9 | M89: VNDR00541 | N89: AGENT00167
A90: TXN00000087 | B90: Monica Threlkeld | C90: Life | D90: 77.65 | E90: 78000 | F90: FL | G90: A | H90: Major Loss | I90: Ambulance | J90: Hesperia | K90: CA | L90: 16 | M90: VNDR00588 | N90: AGENT00792
A91: TXN00000088 | B91: Tasha Bolds | C91: Motor | D91: 82 | E91: 10000 | F91: CO | G91: A | H91: Minor Loss | J91: Lynn Haven | K91: FL | L91: 4 | M91: VNDR00394 | N91: AGENT00001
A92: TXN00000089 | B92: Joseph Walt | C92: Health | D92: 102.63 | E92: 9000 | F92: CA | G92: A | H92: Major Loss | J92: Lowell | K92: MA | L92: 4 | N92: AGENT00955
A93: TXN00000090 | B93: Kate Tito | C93: Health | D93: 199.63 | E93: 16000 | F93: AZ | G93: A | H93: Major Loss | I93: Police | J93: Panama City | K93: FL | L93: 9 | N93: AGENT00428
A94: TXN00000091 | B94: Mary Todd | C94: Travel | D94: 62.02 | E94: 1000 | F94: CT | G94: A | H94: Minor Loss | I94: Ambulance | J94: Oklahoma City | K94: OK | L94: 22 | M94: VNDR00086 | N94: AGENT01136
A95: TXN00000092 | B95: Vivian Kiesel | C95: Health | D95: 153.52 | E95: 19000 | F95: KY | G95: A | H95: Minor Loss | I95: Other | J95: Nashville | K95: TN | L95: 9 | M95: VNDR00532 | N95: AGENT00573
A96: TXN00000093 | B96: Anthony Carpenter | C96: Health | D96: 116.27 | E96: 7000 | F96: VT | G96: A | H96: Major Loss | I96: Ambulance | J96: Oakland | K96: CA | L96: 7 | M96: VNDR00251 | N96: AGENT00474
A97: TXN00000094 | B97: Catherine Wells | C97: Travel | D97: 72.52 | E97: 1000 | F97: OK | G97: A | H97: Total Loss | I97: Police | J97: Moore | K97: OK | L97: 10 | N97: AGENT00908
A98: TXN00000095 | B98: Mariana Waller | C98: Life | D98: 83.23 | E98: 95000 | F98: AL | G98: A | H98: Major Loss | J98: Davidsonville | K98: MD | L98: 6 | M98: VNDR00508 | N98: AGENT00254
A99: TXN00000096 | B99: Brent Fly | C99: Motor | D99: 116.8 | E99: 9000 | F99: DC | G99: A | H99: Total Loss | I99: Ambulance | J99: Anchorage | K99: AK | L99: 13 | N99: AGENT00482
A100: TXN00000097 | B100: Christopher Lee | C100: Life | D100: 82.05 | E100: 15000 | F100: DC | G100: A | H100: Total Loss | J100: Washington | K100: DC | L100: 8 | N100: AGENT00397
A101: TXN00000098 | B101: Donna Delosh | C101: Life | D101: 75.6 | E101: 41000 | F101: TN | G101: A | H101: Total Loss | I101: Police | J101: Panama City | K101: FL | L101: 7 | N101: AGENT00786
...

Sheet Cleaned_Data
A1: CLEANED DATA — Output of data-cleaning steps applied to Raw_Claims_Data
A2: Cleaning steps applied: (1) Blank AUTHORITY_CONTACTED -> 'None' (2) Blank VENDOR_ID -> 'N/A' (3) Derived Fraud flag from CLAIM_STATUS (4) TRIM applied to text fields
A4: TRANSACTION_ID | B4: CUSTOMER_NAME | C4: INSURANCE_TYPE | D4: PREMIUM_AMOUNT | E4: CLAIM_AMOUNT | F4: STATE | G4: CLAIM_STATUS | H4: INCIDENT_SEVERITY | I4: AUTHORITY_CONTACTED_CLEAN | J4: INCIDENT_CITY | K4: INCIDENT_STATE | L4: INCIDENT_HOUR_OF_THE_DAY | M4: VENDOR_ID_CLEAN | N4: AGENT_ID | O4: IsFraud
A5: =Raw_Claims_Data!A4 -> TXN00000001 | B5: =TRIM(Raw_Claims_Data!B4) -> Christopher Demarest | C5: =Raw_Claims_Data!C4 -> Health | D5: =Raw_Claims_Data!D4 -> 157.13 | E5: =Raw_Claims_Data!E4 -> 9000 | F5: =Raw_Claims_Data!F4 -> AZ | G5: =Raw_Claims_Data!G4 -> A | H5: =Raw_Claims_Data!H4 -> Major Loss | I5: =IF(Raw_Claims_Data!I4="","None",Raw_Claims_Data!I4) -> Police | J5: =Raw_Claims_Data!J4 -> Savannah | K5: =Raw_Claims_Data!K4 -> GA | L5: =Raw_Claims_Data!L4 -> 4 | M5: =IF(Raw_Claims_Data!M4="","N/A",Raw_Claims_Data!M4) -> VNDR00556 | N5: =Raw_Claims_Data!N4 -> AGENT00413 | O5: =IF(Raw_Claims_Data!G4="D",1,0) -> 0
A6: =Raw_Claims_Data!A5 -> TXN00000002 | B6: =TRIM(Raw_Claims_Data!B5) -> Ricardo Gatlin | C6: =Raw_Claims_Data!C5 -> Property | D6: =Raw_Claims_Data!D5 -> 141.71 | E6: =Raw_Claims_Data!E5 -> 26000 | F6: =Raw_Claims_Data!F5 -> CO | G6: =Raw_Claims_Data!G5 -> A | H6: =Raw_Claims_Data!H5 -> Total Loss | I6: =IF(Raw_Claims_Data!I5="","None",Raw_Claims_Data!I5) -> Ambulance | J6: =Raw_Claims_Data!J5 -> Montgomery | K6: =Raw_Claims_Data!K5 -> AL | L6: =Raw_Claims_Data!L5 -> 0 | M6: =IF(Raw_Claims_Data!M5="","N/A",Raw_Claims_Data!M5) -> VNDR00592 | N6: =Raw_Claims_Data!N5 -> AGENT00769 | O6: =IF(Raw_Claims_Data!G5="D",1,0) -> 0
A7: =Raw_Claims_Data!A6 -> TXN00000003 | B7: =TRIM(Raw_Claims_Data!B6) -> Lashawn Engles | C7: =Raw_Claims_Data!C6 -> Property | D7: =Raw_Claims_Data!D6 -> 157.24 | E7: =Raw_Claims_Data!E6 -> 13000 | F7: =Raw_Claims_Data!F6 -> CA | G7: =Raw_Claims_Data!G6 -> A | H7: =Raw_Claims_Data!H6 -> Total Loss | I7: =IF(Raw_Claims_Data!I6="","None",Raw_Claims_Data!I6) -> Police | J7: =Raw_Claims_Data!J6 -> Grand Junction | K7: =Raw_Claims_Data!K6 -> CO | L7: =Raw_Claims_Data!L6 -> 19 | M7: =IF(Raw_Claims_Data!M6="","N/A",Raw_Claims_Data!M6) -> VNDR00031 | N7: =Raw_Claims_Data!N6 -> AGENT00883 | O7: =IF(Raw_Claims_Data!G6="D",1,0) -> 0
A8: =Raw_Claims_Data!A7 -> TXN00000004 | B8: =TRIM(Raw_Claims_Data!B7) -> Steven Bassett | C8: =Raw_Claims_Data!C7 -> Health | D8: =Raw_Claims_Data!D7 -> 172.87 | E8: =Raw_Claims_Data!E7 -> 16000 | F8: =Raw_Claims_Data!F7 -> GA | G8: =Raw_Claims_Data!G7 -> A | H8: =Raw_Claims_Data!H7 -> Minor Loss | I8: =IF(Raw_Claims_Data!I7="","None",Raw_Claims_Data!I7) -> Ambulance | J8: =Raw_Claims_Data!J7 -> Savannah | K8: =Raw_Claims_Data!K7 -> GA | L8: =Raw_Claims_Data!L7 -> 12 | M8: =IF(Raw_Claims_Data!M7="","N/A",Raw_Claims_Data!M7) -> VNDR00075 | N8: =Raw_Claims_Data!N7 -> AGENT00278 | O8: =IF(Raw_Claims_Data!G7="D",1,0) -> 0
A9: =Raw_Claims_Data!A8 -> TXN00000005 | B9: =TRIM(Raw_Claims_Data!B8) -> Jason Rodriguez | C9: =Raw_Claims_Data!C8 -> Travel | D9: =Raw_Claims_Data!D8 -> 88.53 | E9: =Raw_Claims_Data!E8 -> 3000 | F9: =Raw_Claims_Data!F8 -> CA | G9: =Raw_Claims_Data!G8 -> A | H9: =Raw_Claims_Data!H8 -> Major Loss | I9: =IF(Raw_Claims_Data!I8="","None",Raw_Claims_Data!I8) -> Police | J9: =Raw_Claims_Data!J8 -> Nashville | K9: =Raw_Claims_Data!K8 -> TN | L9: =Raw_Claims_Data!L8 -> 18 | M9: =IF(Raw_Claims_Data!M8="","N/A",Raw_Claims_Data!M8) -> VNDR00472 | N9: =Raw_Claims_Data!N8 -> AGENT00636 | O9: =IF(Raw_Claims_Data!G8="D",1,0) -> 0
A10: =Raw_Claims_Data!A9 -> TXN00000006 | B10: =TRIM(Raw_Claims_Data!B9) -> Terrance Han | C10: =Raw_Claims_Data!C9 -> Life | D10: =Raw_Claims_Data!D9 -> 87.02 | E10: =Raw_Claims_Data!E9 -> 63000 | F10: =Raw_Claims_Data!F9 -> AZ | G10: =Raw_Claims_Data!G9 -> A | H10: =Raw_Claims_Data!H9 -> Major Loss | I10: =IF(Raw_Claims_Data!I9="","None",Raw_Claims_Data!I9) -> Ambulance | J10: =Raw_Claims_Data!J9 -> Glendale | K10: =Raw_Claims_Data!K9 -> AZ | L10: =Raw_Claims_Data!L9 -> 0 | M10: =IF(Raw_Claims_Data!M9="","N/A",Raw_Claims_Data!M9) -> N/A | N10: =Raw_Claims_Data!N9 -> AGENT00402 | O10: =IF(Raw_Claims_Data!G9="D",1,0) -> 0
A11: =Raw_Claims_Data!A10 -> TXN00000007 | B11: =TRIM(Raw_Claims_Data!B10) -> Dennis Johnson | C11: =Raw_Claims_Data!C10 -> Health | D11: =Raw_Claims_Data!D10 -> 197.23 | E11: =Raw_Claims_Data!E10 -> 3000 | F11: =Raw_Claims_Data!F10 -> FL | G11: =Raw_Claims_Data!G10 -> A | H11: =Raw_Claims_Data!H10 -> Major Loss | I11: =IF(Raw_Claims_Data!I10="","None",Raw_Claims_Data!I10) -> Police | J11: =Raw_Claims_Data!J10 -> Manchester | K11: =Raw_Claims_Data!K10 -> CT | L11: =Raw_Claims_Data!L10 -> 10 | M11: =IF(Raw_Claims_Data!M10="","N/A",Raw_Claims_Data!M10) -> VNDR00150 | N11: =Raw_Claims_Data!N10 -> AGENT00322 | O11: =IF(Raw_Claims_Data!G10="D",1,0) -> 0
A12: =Raw_Claims_Data!A11 -> TXN00000008 | B12: =TRIM(Raw_Claims_Data!B11) -> Maryalice Martinez | C12: =Raw_Claims_Data!C11 -> Motor | D12: =Raw_Claims_Data!D11 -> 83.77 | E12: =Raw_Claims_Data!E11 -> 8000 | F12: =Raw_Claims_Data!F11 -> GA | G12: =Raw_Claims_Data!G11 -> A | H12: =Raw_Claims_Data!H11 -> Total Loss | I12: =IF(Raw_Claims_Data!I11="","None",Raw_Claims_Data!I11) -> Police | J12: =Raw_Claims_Data!J11 -> Panama City Beach | K12: =Raw_Claims_Data!K11 -> FL | L12: =Raw_Claims_Data!L11 -> 10 | M12: =IF(Raw_Claims_Data!M11="","N/A",Raw_Claims_Data!M11) -> VNDR00326 | N12: =Raw_Claims_Data!N11 -> AGENT00152 | O12: =IF(Raw_Claims_Data!G11="D",1,0) -> 0
A13: =Raw_Claims_Data!A12 -> TXN00000009 | B13: =TRIM(Raw_Claims_Data!B12) -> Nicholas Hamilton | C13: =Raw_Claims_Data!C12 -> Motor | D13: =Raw_Claims_Data!D12 -> 82.14 | E13: =Raw_Claims_Data!E12 -> 5000 | F13: =Raw_Claims_Data!F12 -> KY | G13: =Raw_Claims_Data!G12 -> A | H13: =Raw_Claims_Data!H12 -> Major Loss | I13: =IF(Raw_Claims_Data!I12="","None",Raw_Claims_Data!I12) -> Police | J13: =Raw_Claims_Data!J12 -> Glendale | K13: =Raw_Claims_Data!K12 -> AZ | L13: =Raw_Claims_Data!L12 -> 22 | M13: =IF(Raw_Claims_Data!M12="","N/A",Raw_Claims_Data!M12) -> VNDR00437 | N13: =Raw_Claims_Data!N12 -> AGENT00450 | O13: =IF(Raw_Claims_Data!G12="D",1,0) -> 0
A14: =Raw_Claims_Data!A13 -> TXN00000010 | B14: =TRIM(Raw_Claims_Data!B13) -> Nicholas Honokaupu | C14: =Raw_Claims_Data!C13 -> Travel | D14: =Raw_Claims_Data!D13 -> 71.29 | E14: =Raw_Claims_Data!E13 -> 4000 | F14: =Raw_Claims_Data!F13 -> AL | G14: =Raw_Claims_Data!G13 -> A | H14: =Raw_Claims_Data!H13 -> Major Loss | I14: =IF(Raw_Claims_Data!I13="","None",Raw_Claims_Data!I13) -> None | J14: =Raw_Claims_Data!J13 -> San Leandro | K14: =Raw_Claims_Data!K13 -> CA | L14: =Raw_Claims_Data!L13 -> 4 | M14: =IF(Raw_Claims_Data!M13="","N/A",Raw_Claims_Data!M13) -> N/A | N14: =Raw_Claims_Data!N13 -> AGENT00682 | O14: =IF(Raw_Claims_Data!G13="D",1,0) -> 0
A15: =Raw_Claims_Data!A14 -> TXN00000011 | B15: =TRIM(Raw_Claims_Data!B14) -> Janet Watts | C15: =Raw_Claims_Data!C14 -> Life | D15: =Raw_Claims_Data!D14 -> 61.45 | E15: =Raw_Claims_Data!E14 -> 92000 | F15: =Raw_Claims_Data!F14 -> CT | G15: =Raw_Claims_Data!G14 -> A | H15: =Raw_Claims_Data!H14 -> Major Loss | I15: =IF(Raw_Claims_Data!I14="","None",Raw_Claims_Data!I14) -> Ambulance | J15: =Raw_Claims_Data!J14 -> Crofton | K15: =Raw_Claims_Data!K14 -> MD | L15: =Raw_Claims_Data!L14 -> 23 | M15: =IF(Raw_Claims_Data!M14="","N/A",Raw_Claims_Data!M14) -> VNDR00163 | N15: =Raw_Claims_Data!N14 -> AGENT01091 | O15: =IF(Raw_Claims_Data!G14="D",1,0) -> 0
A16: =Raw_Claims_Data!A15 -> TXN00000012 | B16: =TRIM(Raw_Claims_Data!B15) -> Patricia Garrett | C16: =Raw_Claims_Data!C15 -> Motor | D16: =Raw_Claims_Data!D15 -> 101.15 | E16: =Raw_Claims_Data!E15 -> 8000 | F16: =Raw_Claims_Data!F15 -> TN | G16: =Raw_Claims_Data!G15 -> D | H16: =Raw_Claims_Data!H15 -> Major Loss | I16: =IF(Raw_Claims_Data!I15="","None",Raw_Claims_Data!I15) -> Ambulance | J16: =Raw_Claims_Data!J15 -> Manchester | K16: =Raw_Claims_Data!K15 -> CT | L16: =Raw_Claims_Data!L15 -> 3 | M16: =IF(Raw_Claims_Data!M15="","N/A",Raw_Claims_Data!M15) -> N/A | N16: =Raw_Claims_Data!N15 -> AGENT00288 | O16: =IF(Raw_Claims_Data!G15="D",1,0) -> 1
... A3004: =Raw_Claims_Data!A3003 -> TXN00003000 | B3004: =TRIM(Raw_Claims_Data!B3003) -> John Leath | C3004: =Raw_Claims_Data!C3003 -> Mobile | D3004: =Raw_Claims_Data!D3003 -> 8.73 | E3004: =Raw_Claims_Data!E3003 -> 500 | F3004: =Raw_Claims_Data!F3003 -> AL | G3004: =Raw_Claims_Data!G3003 -> A | H3004: =Raw_Claims_Data!H3003 -> Major Loss | I3004: =IF(Raw_Claims_Data!I3003="","None",Raw_Claims_Data!I3003) -> Other | J3004: =Raw_Claims_Data!J3003 -> Arvada | K3004: =Raw_Claims_Data!K3003 -> CO | L3004: =Raw_Claims_Data!L3003 -> 3 | M3004: =IF(Raw_Claims_Data!M3003="","N/A",Raw_Claims_Data!M3003) -> VNDR00284 | N3004: =Raw_Claims_Data!N3003 -> AGENT00942 | O3004: =IF(Raw_Claims_Data!G3003="D",1,0) -> 0

Sheet Pivot_Analysis
A1: PIVOT-STYLE SUMMARY — Claims & Fraud by Insurance Type and State
A2: Built with SUMIFS/COUNTIFS off Cleaned_Data (3,000-row sample). To convert to a live native PivotTable: select Cleaned_Data!A4:O3004 -> Insert -> PivotTable.
A4: By Insurance Type
A5: INSURANCE_TYPE | B5: Total Claims | C5: Fraud Claims | D5: Fraud Rate % | E5: Total Claim Amount | F5: Avg Claim Amount
A6: Health | B6: =COUNTIFS(Cleaned_Data!$C$5:$C$3004,A6) -> 499 | C6: =COUNTIFS(Cleaned_Data!$C$5:$C$3004,A6,Cleaned_Data!$O$5:$O$3004,1) -> 33 | D6: =IF(B6=0,0,C6/B6) -> 0.066132265 | E6: =SUMIFS(Cleaned_Data!$E$5:$E$3004,Cleaned_Data!$C$5:$C$3004,A6) -> 5340000 | F6: =IF(B6=0,0,E6/B6) -> 10701.403
A7: Life | B7: =COUNTIFS(Cleaned_Data!$C$5:$C$3004,A7) -> 498 | C7: =COUNTIFS(Cleaned_Data!$C$5:$C$3004,A7,Cleaned_Data!$O$5:$O$3004,1) -> 22 | D7: =IF(B7=0,0,C7/B7) -> 0.044176707 | E7: =SUMIFS(Cleaned_Data!$E$5:$E$3004,Cleaned_Data!$C$5:$C$3004,A7) -> 27299000 | F7: =IF(B7=0,0,E7/B7) -> 54817.269
A8: Mobile | B8: =COUNTIFS(Cleaned_Data!$C$5:$C$3004,A8) -> 528 | C8: =COUNTIFS(Cleaned_Data!$C$5:$C$3004,A8,Cleaned_Data!$O$5:$O$3004,1) -> 29 | D8: =IF(B8=0,0,C8/B8) -> 0.054924242 | E8: =SUMIFS(Cleaned_Data!$E$5:$E$3004,Cleaned_Data!$C$5:$C$3004,A8) -> 213800 | F8: =IF(B8=0,0,E8/B8) -> 404.92424
A9: Motor | B9: =COUNTIFS(Cleaned_Data!$C$5:$C$3004,A9) -> 472 | C9: =COUNTIFS(Cleaned_Data!$C$5:$C$3004,A9,Cleaned_Data!$O$5:$O$3004,1) -> 30 | D9: =IF(B9=0,0,C9/B9) -> 0.063559322 | E9: =SUMIFS(Cleaned_Data!$E$5:$E$3004,Cleaned_Data!$C$5:$C$3004,A9) -> 2608000 | F9: =IF(B9=0,0,E9/B9) -> 5525.4237
A10: Property | B10: =COUNTIFS(Cleaned_Data!$C$5:$C$3004,A10) -> 507 | C10: =COUNTIFS(Cleaned_Data!$C$5:$C$3004,A10,Cleaned_Data!$O$5:$O$3004,1) -> 26 | D10: =IF(B10=0,0,C10/B10) -> 0.051282051 | E10: =SUMIFS(Cleaned_Data!$E$5:$E$3004,Cleaned_Data!$C$5:$C$3004,A10) -> 12538000 | F10: =IF(B10=0,0,E10/B10) -> 24729.783
A11: Travel | B11: =COUNTIFS(Cleaned_Data!$C$5:$C$3004,A11) -> 496 | C11: =COUNTIFS(Cleaned_Data!$C$5:$C$3004,A11,Cleaned_Data!$O$5:$O$3004,1) -> 27 | D11: =IF(B11=0,0,C11/B11) -> 0.054435484 | E11: =SUMIFS(Cleaned_Data!$E$5:$E$3004,Cleaned_Data!$C$5:$C$3004,A11) -> 1463000 | F11: =IF(B11=0,0,E11/B11) -> 2949.5968
A13: By State (Top 10 by Claim Volume)
A14: STATE | B14: Total Claims | C14: Fraud Claims | D14: Fraud Rate % | E14: Total Claim Amount
A15: CA | B15: =COUNTIFS(Cleaned_Data!$F$5:$F$3004,A15) -> 310 | C15: =COUNTIFS(Cleaned_Data!$F$5:$F$3004,A15,Cleaned_Data!$O$5:$O$3004,1) -> 19 | D15: =IF(B15=0,0,C15/B15) -> 0.061290323 | E15: =SUMIFS(Cleaned_Data!$E$5:$E$3004,Cleaned_Data!$F$5:$F$3004,A15) -> 5371600
A16: CO | B16: =COUNTIFS(Cleaned_Data!$F$5:$F$3004,A16) -> 207 | C16: =COUNTIFS(Cleaned_Data!$F$5:$F$3004,A16,Cleaned_Data!$O$5:$O$3004,1) -> 13 | D16: =IF(B16=0,0,C16/B16) -> 0.062801932 | E16: =SUMIFS(Cleaned_Data!$E$5:$E$3004,Cleaned_Data!$F$5:$F$3004,A16) -> 3109700
A17: GA | B17: =COUNTIFS(Cleaned_Data!$F$5:$F$3004,A17) -> 195 | C17: =COUNTIFS(Cleaned_Data!$F$5:$F$3004,A17,Cleaned_Data!$O$5:$O$3004,1) -> 14 | D17: =IF(B17=0,0,C17/B17) -> 0.071794872 | E17: =SUMIFS(Cleaned_Data!$E$5:$E$3004,Cleaned_Data!$F$5:$F$3004,A17) -> 2953500
A18: CT | B18: =COUNTIFS(Cleaned_Data!$F$5:$F$3004,A18) -> 195 | C18: =COUNTIFS(Cleaned_Data!$F$5:$F$3004,A18,Cleaned_Data!$O$5:$O$3004,1) -> 11 | D18: =IF(B18=0,0,C18/B18) -> 0.056410256 | E18: =SUMIFS(Cleaned_Data!$E$5:$E$3004,Cleaned_Data!$F$5:$F$3004,A18) -> 2977900
A19: TN | B19: =COUNTIFS(Cleaned_Data!$F$5:$F$3004,A19) -> 195 | C19: =COUNTIFS(Cleaned_Data!$F$5:$F$3004,A19,Cleaned_Data!$O$5:$O$3004,1) -> 15 | D19: =IF(B19=0,0,C19/B19) -> 0.076923077 | E19: =SUMIFS(Cleaned_Data!$E$5:$E$3004,Cleaned_Data!$F$5:$F$3004,A19) -> 3624800
A20: KY | B20: =COUNTIFS(Cleaned_Data!$F$5:$F$3004,A20) -> 193 | C20: =COUNTIFS(Cleaned_Data!$F$5:$F$3004,A20,Cleaned_Data!$O$5:$O$3004,1) -> 12 | D20: =IF(B20=0,0,C20/B20) -> 0.062176166 | E20: =SUMIFS(Cleaned_Data!$E$5:$E$3004,Cleaned_Data!$F$5:$F$3004,A20) -> 2753500
A21: AR | B21: =COUNTIFS(Cleaned_Data!$F$5:$F$3004,A21) -> 193 | C21: =COUNTIFS(Cleaned_Data!$F$5:$F$3004,A21,Cleaned_Data!$O$5:$O$3004,1) -> 10 | D21: =IF(B21=0,0,C21/B21) -> 0.051813472 | E21: =SUMIFS(Cleaned_Data!$E$5:$E$3004,Cleaned_Data!$F$5:$F$3004,A21) -> 3452600
A22: FL | B22: =COUNTIFS(Cleaned_Data!$F$5:$F$3004,A22) -> 189 | C22: =COUNTIFS(Cleaned_Data!$F$5:$F$3004,A22,Cleaned_Data!$O$5:$O$3004,1) -> 8 | D22: =IF(B22=0,0,C22/B22) -> 0.042328042 | E22: =SUMIFS(Cleaned_Data!$E$5:$E$3004,Cleaned_Data!$F$5:$F$3004,A22) -> 3123300
A23: DC | B23: =COUNTIFS(Cleaned_Data!$F$5:$F$3004,A23) -> 185 | C23: =COUNTIFS(Cleaned_Data!$F$5:$F$3004,A23,Cleaned_Data!$O$5:$O$3004,1) -> 14 | D23: =IF(B23=0,0,C23/B23) -> 0.075675676 | E23: =SUMIFS(Cleaned_Data!$E$5:$E$3004,Cleaned_Data!$F$5:$F$3004,A23) -> 3259100
A24: AZ | B24: =COUNTIFS(Cleaned_Data!$F$5:$F$3004,A24) -> 177 | C24: =COUNTIFS(Cleaned_Data!$F$5:$F$3004,A24,Cleaned_Data!$O$5:$O$3004,1) -> 9 | D24: =IF(B24=0,0,C24/B24) -> 0.050847458 | E24: =SUMIFS(Cleaned_Data!$E$5:$E$3004,Cleaned_Data!$F$5:$F$3004,A24) -> 3386600

Sheet Lookup_Examples
A1: LOOKUP EXAMPLES — INDEX/MATCH pulling Agent & Vendor details across sheets
A2: Demonstrates cross-sheet lookups: Cleaned_Data -> Agents sheet and Cleaned_Data -> Vendors sheet
A4: TRANSACTION_ID | B4: AGENT_ID | C4: Agent Name (INDEX/MATCH) | D4: Agent City (INDEX/MATCH) | E4: VENDOR_ID | F4: Vendor Name (INDEX/MATCH) | G4: Vendor City (INDEX/MATCH)
A5: =Cleaned_Data!A5 -> TXN00000001 | B5: =Cleaned_Data!N5 -> AGENT00413 | C5: =IFERROR(INDEX(Agents!$B$4:$B$1203,MATCH(B5,Agents!$A$4:$A$1203,0)),"Not Found") -> Amy Wangler | D5: =IFERROR(INDEX(Agents!$F$4:$F$1203,MATCH(B5,Agents!$A$4:$A$1203,0)),"Not Found") -> Nashville | E5: =Cleaned_Data!M5 -> VNDR00556 | F5: =IFERROR(INDEX(Vendors!$B$4:$B$603,MATCH(E5,Vendors!$A$4:$A$603,0)),"No Vendor / N-A") -> Ramsey Inc | G5: =IFERROR(INDEX(Vendors!$E$4:$E$603,MATCH(E5,Vendors!$A$4:$A$603,0)),"No Vendor / N-A") -> Panama City
A6: =Cleaned_Data!A6 -> TXN00000002 | B6: =Cleaned_Data!N6 -> AGENT00769 | C6: =IFERROR(INDEX(Agents!$B$4:$B$1203,MATCH(B6,Agents!$A$4:$A$1203,0)),"Not Found") -> Jessica Montez | D6: =IFERROR(INDEX(Agents!$F$4:$F$1203,MATCH(B6,Agents!$A$4:$A$1203,0)),"Not Found") -> Glendale | E6: =Cleaned_Data!M6 -> VNDR00592 | F6: =IFERROR(INDEX(Vendors!$B$4:$B$603,MATCH(E6,Vendors!$A$4:$A$603,0)),"No Vendor / N-A") -> Morales, Campbell and Washington | G6: =IFERROR(INDEX(Vendors!$E$4:$E$603,MATCH(E6,Vendors!$A$4:$A$603,0)),"No Vendor / N-A") -> Fayetteville
A7: =Cleaned_Data!A7 -> TXN00000003 | B7: =Cleaned_Data!N7 -> AGENT00883 | C7: =IFERROR(INDEX(Agents!$B$4:$B$1203,MATCH(B7,Agents!$A$4:$A$1203,0)),"Not Found") -> Howard Smith | D7: =IFERROR(INDEX(Agents!$F$4:$F$1203,MATCH(B7,Agents!$A$4:$A$1203,0)),"Not Found") -> Montgomery | E7: =Cleaned_Data!M7 -> VNDR00031 | F7: =IFERROR(INDEX(Vendors!$B$4:$B$603,MATCH(E7,Vendors!$A$4:$A$603,0)),"No Vendor / N-A") -> Johnson Ltd | G7: =IFERROR(INDEX(Vendors!$E$4:$E$603,MATCH(E7,Vendors!$A$4:$A$603,0)),"No Vendor / N-A") -> Fayetteville
A8: =Cleaned_Data!A8 -> TXN00000004 | B8: =Cleaned_Data!N8 -> AGENT00278 | C8: =IFERROR(INDEX(Agents!$B$4:$B$1203,MATCH(B8,Agents!$A$4:$A$1203,0)),"Not Found") -> Patricia Tucker | D8: =IFERROR(INDEX(Agents!$F$4:$F$1203,MATCH(B8,Agents!$A$4:$A$1203,0)),"Not Found") -> Norman | E8: =Cleaned_Data!M8 -> VNDR00075 | F8: =IFERROR(INDEX(Vendors!$B$4:$B$603,MATCH(E8,Vendors!$A$4:$A$603,0)),"No Vendor / N-A") -> Blackwell-Foster | G8: =IFERROR(INDEX(Vendors!$E$4:$E$603,MATCH(E8,Vendors!$A$4:$A$603,0)),"No Vendor / N-A") -> Nashville
A9: =Cleaned_Data!A9 -> TXN00000005 | B9: =Cleaned_Data!N9 -> AGENT00636 | C9: =IFERROR(INDEX(Agents!$B$4:$B$1203,MATCH(B9,Agents!$A$4:$A$1203,0)),"Not Found") -> Brenda Bean | D9: =IFERROR(INDEX(Agents!$F$4:$F$1203,MATCH(B9,Agents!$A$4:$A$1203,0)),"Not Found") -> Glen Burnie | E9: =Cleaned_Data!M9 -> VNDR00472 | F9: =IFERROR(INDEX(Vendors!$B$4:$B$603,MATCH(E9,Vendors!$A$4:$A$603,0)),"No Vendor / N-A") -> Evans-Scott | G9: =IFERROR(INDEX(Vendors!$E$4:$E$603,MATCH(E9,Vendors!$A$4:$A$603,0)),"No Vendor / N-A") -> Washington
A10: =Cleaned_Data!A10 -> TXN00000006 | B10: =Cleaned_Data!N10 -> AGENT00402 | C10: =IFERROR(INDEX(Agents!$B$4:$B$1203,MATCH(B10,Agents!$A$4:$A$1203,0)),"Not Found") -> Luciano Jackson | D10: =IFERROR(INDEX(Agents!$F$4:$F$1203,MATCH(B10,Agents!$A$4:$A$1203,0)),"Not Found") -> Bakersfield | E10: =Cleaned_Data!M10 -> N/A | F10: =IFERROR(INDEX(Vendors!$B$4:$B$603,MATCH(E10,Vendors!$A$4:$A$603,0)),"No Vendor / N-A") -> No Vendor / N-A | G10: =IFERROR(INDEX(Vendors!$E$4:$E$603,MATCH(E10,Vendors!$A$4:$A$603,0)),"No Vendor / N-A") -> No Vendor / N-A
A11: =Cleaned_Data!A11 -> TXN00000007 | B11: =Cleaned_Data!N11 -> AGENT00322 | C11: =IFERROR(INDEX(Agents!$B$4:$B$1203,MATCH(B11,Agents!$A$4:$A$1203,0)),"Not Found") -> Edgar Talley | D11: =IFERROR(INDEX(Agents!$F$4:$F$1203,MATCH(B11,Agents!$A$4:$A$1203,0)),"Not Found") -> East Longmeadow | E11: =Cleaned_Data!M11 -> VNDR00150 | F11: =IFERROR(INDEX(Vendors!$B$4:$B$603,MATCH(E11,Vendors!$A$4:$A$603,0)),"No Vendor / N-A") -> Moreno LLC | G11: =IFERROR(INDEX(Vendors!$E$4:$E$603,MATCH(E11,Vendors!$A$4:$A$603,0)),"No Vendor / N-A") -> Nashville
A12: =Cleaned_Data!A12 -> TXN00000008 | B12: =Cleaned_Data!N12 -> AGENT00152 | C12: =IFERROR(INDEX(Agents!$B$4:$B$1203,MATCH(B12,Agents!$A$4:$A$1203,0)),"Not Found") -> John Hensel | D12: =IFERROR(INDEX(Agents!$F$4:$F$1203,MATCH(B12,Agents!$A$4:$A$1203,0)),"Not Found") -> Louisville | E12: =Cleaned_Data!M12 -> VNDR00326 | F12: =IFERROR(INDEX(Vendors!$B$4:$B$603,MATCH(E12,Vendors!$A$4:$A$603,0)),"No Vendor / N-A") -> Stewart Ltd | G12: =IFERROR(INDEX(Vendors!$E$4:$E$603,MATCH(E12,Vendors!$A$4:$A$603,0)),"No Vendor / N-A") -> Washington
A13: =Cleaned_Data!A13 -> TXN00000009 | B13: =Cleaned_Data!N13 -> AGENT00450 | C13: =IFERROR(INDEX(Agents!$B$4:$B$1203,MATCH(B13,Agents!$A$4:$A$1203,0)),"Not Found") -> Peter Thomas | D13: =IFERROR(INDEX(Agents!$F$4:$F$1203,MATCH(B13,Agents!$A$4:$A$1203,0)),"Not Found") -> Washington | E13: =Cleaned_Data!M13 -> VNDR00437 | F13: =IFERROR(INDEX(Vendors!$B$4:$B$603,MATCH(E13,Vendors!$A$4:$A$603,0)),"No Vendor / N-A") -> Hanson Inc | G13: =IFERROR(INDEX(Vendors!$E$4:$E$603,MATCH(E13,Vendors!$A$4:$A$603,0)),"No Vendor / N-A") -> Fayetteville
A14: =Cleaned_Data!A14 -> TXN00000010 | B14: =Cleaned_Data!N14 -> AGENT00682 | C14: =IFERROR(INDEX(Agents!$B$4:$B$1203,MATCH(B14,Agents!$A$4:$A$1203,0)),"Not Found") -> Michael Ortiz | D14: =IFERROR(INDEX(Agents!$F$4:$F$1203,MATCH(B14,Agents!$A$4:$A$1203,0)),"Not Found") -> Anchorage | E14: =Cleaned_Data!M14 -> N/A | F14: =IFERROR(INDEX(Vendors!$B$4:$B$603,MATCH(E14,Vendors!$A$4:$A$603,0)),"No Vendor / N-A") -> No Vendor / N-A | G14: =IFERROR(INDEX(Vendors!$E$4:$E$603,MATCH(E14,Vendors!$A$4:$A$603,0)),"No Vendor / N-A") -> No Vendor / N-A
A15: =Cleaned_Data!A15 -> TXN00000011 | B15: =Cleaned_Data!N15 -> AGENT01091 | C15: =IFERROR(INDEX(Agents!$B$4:$B$1203,MATCH(B15,Agents!$A$4:$A$1203,0)),"Not Found") -> Joshua Losey | D15: =IFERROR(INDEX(Agents!$F$4:$F$1203,MATCH(B15,Agents!$A$4:$A$1203,0)),"Not Found") -> Montgomery | E15: =Cleaned_Data!M15 -> VNDR00163 | F15: =IFERROR(INDEX(Vendors!$B$4:$B$603,MATCH(E15,Vendors!$A$4:$A$603,0)),"No Vendor / N-A") -> Foster-Sanchez | G15: =IFERROR(INDEX(Vendors!$E$4:$E$603,MATCH(E15,Vendors!$A$4:$A$603,0)),"No Vendor / N-A") -> Fremont
A16: =Cleaned_Data!A16 -> TXN00000012 | B16: =Cleaned_Data!N16 -> AGENT00288 | C16: =IFERROR(INDEX(Agents!$B$4:$B$1203,MATCH(B16,Agents!$A$4:$A$1203,0)),"Not Found") -> Michael Fowler | D16: =IFERROR(INDEX(Agents!$F$4:$F$1203,MATCH(B16,Agents!$A$4:$A$1203,0)),"Not Found") -> Guthrie | E16: =Cleaned_Data!M16 -> N/A | F16: =IFERROR(INDEX(Vendors!$B$4:$B$603,MATCH(E16,Vendors!$A$4:$A$603,0)),"No Vendor / N-A") -> No Vendor / N-A | G16: =IFERROR(INDEX(Vendors!$E$4:$E$603,MATCH(E16,Vendors!$A$4:$A$603,0)),"No Vendor / N-A") -> No Vendor / N-A
... A64: =Cleaned_Data!A64 -> TXN00000060 | B64: =Cleaned_Data!N64 -> AGENT00288 | C64: =IFERROR(INDEX(Agents!$B$4:$B$1203,MATCH(B64,Agents!$A$4:$A$1203,0)),"Not Found") -> Michael Fowler | D64: =IFERROR(INDEX(Agents!$F$4:$F$1203,MATCH(B64,Agents!$A$4:$A$1203,0)),"Not Found") -> Guthrie | E64: =Cleaned_Data!M64 -> N/A | F64: =IFERROR(INDEX(Vendors!$B$4:$B$603,MATCH(E64,Vendors!$A$4:$A$603,0)),"No Vendor / N-A") -> No Vendor / N-A | G64: =IFERROR(INDEX(Vendors!$E$4:$E$603,MATCH(E64,Vendors!$A$4:$A$603,0)),"No Vendor / N-A") -> No Vendor / N-A

Sheet Agents
A1: LOOKUP TABLE — Agents (from employee_data_2_.csv)
A3: AGENT_ID | B3: AGENT_NAME | C3: DATE_OF_JOINING | D3: ADDRESS_LINE1 | E3: ADDRESS_LINE2 | F3: CITY | G3: STATE | H3: POSTAL_CODE | I3: EMP_ROUTING_NUMBER | J3: EMP_ACCT_NUMBER
A4: AGENT00001 | B4: Ray Johns | C4: 1993-06-05 | D4: 1402 Maggies Way | F4: Waterbury Center | G4: VT | H4: 5677 | I4: 34584958 | J4: HKUN51252328472585
A5: AGENT00002 | B5: Angelo Borjon | C5: 2005-12-27 | D5: 414 Tanya Pass | F5: Panama City | G5: FL | H5: 32404 | I5: 107363763 | J5: OPIS19290040088204
A6: AGENT00003 | B6: Candy Spellman | C6: 2003-09-02 | D6: 606 National Street | E6: #306 | F6: Fayetteville | G6: AR | H6: 72701 | I6: 81744097 | J6: YSCJ67489688482590
A7: AGENT00004 | B7: Mary Smith | C7: 2004-09-23 | D7: 235 Hugh Thomas Drive | F7: Panama City | G7: FL | H7: 32404 | I7: 67563771 | J7: ZANG21285355574581
A8: AGENT00005 | B8: Mildred Diaz | C8: 2011-06-21 | D8: 3426 Broadview Street | F8: Montgomery | G8: AL | H8: 36110 | I8: 114951317 | J8: DZFS82244494451134
A9: AGENT00006 | B9: Linda Butler | C9: 2000-09-02 | D9: 10383 Eagle River Lane | F9: Anchorage | G9: AK | H9: 99577 | I9: 82970527 | J9: TIDG93550966796680
A10: AGENT00007 | B10: Michael Hoskins | C10: 1993-10-26 | D10: 5011 West New World Drive | F10: Glendale | G10: AZ | H10: 85302 | I10: 53819552 | J10: OVFE89299102977291
A11: AGENT00008 | B11: Carolyn Quesada | C11: 2003-11-15 | D11: 2538 East 40th Plaza | F11: Panama City | G11: FL | H11: 32405 | I11: 58311521 | J11: HOSW68784912234194
A12: AGENT00009 | B12: Marilyn Allen | C12: 2009-12-24 | D12: 4840 Reservoir Road Northwest | F12: Washington | G12: DC | H12: 20007 | I12: 66645522 | J12: NXRT72066780733033
A13: AGENT00010 | B13: Bernard Haug | C13: 1992-09-04 | D13: 2278 North Windswept Lane | F13: Fayetteville | G13: AR | H13: 72703 | I13: 75517997 | J13: ADZX82914131196683
A14: AGENT00011 | B14: Nancy Coronado | C14: 2002-01-31 | D14: 357 Chaplin Street Southeast | F14: Washington | G14: DC | H14: 20019 | I14: 28574903 | J14: CEIG07819775081568
A15: AGENT00012 | B15: Jeffrey Forbis | C15: 2010-08-05 | D15: 2619 North Quality Lane | E15: #315 | F15: Fayetteville | G15: AR | H15: 72703 | I15: 121484709 | J15: IQRF67979220911116
A16: AGENT00013 | B16: Carolyn Jones | C16: 2004-06-03 | D16: 6214 Herzog Street | F16: Oakland | G16: CA | H16: 94608 | I16: 22235031 | J16: OBTC64157859730067
A17: AGENT00014 | B17: Larry Dryer | C17: 2005-02-22 | D17: 6630 MacArthur Boulevard | E17: #19 | F17: Oakland | G17: CA | H17: 94605 | I17: 20663647 | J17: FXNK82621091893099
A18: AGENT00015 | B18: Charles George | C18: 1998-01-31 | D18: 4717 Forest Hills Drive | F18: Noble | G18: OK | H18: 73068 | I18: 112506777 | J18: PEUK68232037630713
A19: AGENT00016 | B19: Lawrence French | C19: 2001-03-27 | D19: 6223 Kilmer Loop | E19: #206 | F19: Arvada | G19: CO | H19: 80403 | I19: 117354623 | J19: FHIJ73978869917642
A20: AGENT00017 | B20: Robert Gordon | C20: 2003-09-09 | D20: 1100 Cleveland Street | F20: Fayetteville | G20: AR | H20: 72701 | I20: 33587927 | J20: SXOO45515923150315
A21: AGENT00018 | B21: Rita Allaire | C21: 1990-09-30 | D21: 9457 Winfield Place | F21: Montgomery | G21: AL | H21: 36117 | I21: 31655398 | J21: LROE33621282470193
A22: AGENT00019 | B22: Letitia Friedman | C22: 2015-03-03 | D22: 2728 Hale Avenue | F22: Louisville | G22: KY | H22: 40211 | I22: 36932870 | J22: HQBC86092587568338
A23: AGENT00020 | B23: Freddy Kelly | C23: 2004-11-07 | D23: 514 East 38th Street | F23: Savannah | G23: GA | H23: 31401 | I23: 70571857 | J23: CSDO98178213155606
A24: AGENT00021 | B24: Robert Barnes | C24: 1992-08-01 | D24: 54 Pine Meadow Drive | F24: Hyde Park | G24: VT | H24: 5655 | I24: 60304500 | J24: QBCN62231485753777
A25: AGENT00022 | B25: Jeffery Mcbride | C25: 1997-01-13 | D25: 2032 4th Street Northwest | F25: Washington | G25: DC | H25: 20001 | I25: 62349783 | J25: QESE68363490537237
A26: AGENT00023 | B26: Amy Venice | C26: 2009-12-11 | D26: 386 Pratt Road | G26: VT | H26: 5033 | I26: 50361922 | J26: AQEJ74503862345483
A27: AGENT00024 | B27: Herbert Harris | C27: 1991-05-10 | D27: 2433 Southwest 36th Street | F27: Oklahoma City | G27: OK | H27: 73109 | I27: 13102173 | J27: ZOKM64306961771096
A28: AGENT00025 | B28: Elizabeth Mobley | C28: 2010-12-08 | D28: 19020 North 68th Avenue | F28: Glendale | G28: AZ | H28: 85308 | I28: 60796891 | J28: LJXW49594989067332
A29: AGENT00026 | B29: Josephine Amorosi | C29: 2011-09-23 | D29: 1650 North Sang Avenue | E29: #211 | F29: Fayetteville | G29: AR | H29: 72703 | I29: 90344527 | J29: OFDO18308945661277
A30: AGENT00027 | B30: Jaqueline Hanson | C30: 2010-04-20 | D30: 6506 North Lagoon Drive | F30: Panama City Beach | G30: FL | H30: 32408 | I30: 28032351 | J30: HNDV98515562374050
A31: AGENT00028 | B31: Pam Evans | C31: 2012-07-30 | D31: 5575 South Dakota Avenue Northeast | F31: Washington | G31: DC | H31: 20011 | I31: 73180915 | J31: FMOY86795555984406
A32: AGENT00029 | B32: Heather Cantwell | C32: 1995-04-19 | D32: 6521 North 65th Avenue | E32: #1D | F32: Glendale | G32: AZ | H32: 85301 | I32: 67567298 | J32: YLQJ78001413271998
A33: AGENT00030 | B33: Georgia Kenny | C33: 1996-02-21 | D33: 33300 Mission Boulevard | E33: #APT 174 | F33: Union City | G33: CA | H33: 94587 | I33: 82810894 | J33: NKHZ89593337512392
A34: AGENT00031 | B34: Grace Rogers | C34: 2007-09-16 | D34: 5436 Dorbrandt Street | E34: #APT 000002 | F34: Anchorage | G34: AK | H34: 99518 | I34: 94846982 | J34: VQTA51524709318568
A35: AGENT00032 | B35: Russell Frost | C35: 1991-08-07 | D35: 329 Mill Road | F35: Montpelier | G35: VT | H35: 5602 | I35: 108142831 | J35: OBQY16641865636698
A36: AGENT00033 | B36: Arturo Cole | C36: 1996-11-15 | D36: 72 Salmon Road | F36: Alameda | G36: CA | H36: 94502 | I36: 73671657 | J36: VQGP85136893422980
A37: AGENT00034 | B37: Yvonne Sanders | C37: 2007-06-01 | D37: 3808 Richland Avenue | F37: Nashville | G37: TN | H37: 37205 | I37: 36577439 | J37: QVPX46594207904513
A38: AGENT00035 | B38: David Dolan | C38: 1996-11-22 | D38: 849 East Victoria Street | E38: #204 | F38: Carson | G38: CA | H38: 90746 | I38: 63520475 | J38: YMXC17374311568980
A39: AGENT00036 | B39: Gregory Williamson | C39: 1991-09-11 | D39: 1460 Berger Street | F39: Odenton | G39: MD | H39: 21113 | I39: 41131983 | J39: CTEP60853938359624
A40: AGENT00037 | B40: Teresa Garcia | C40: 2016-12-19 | D40: 140 West Cooper Avenue | F40: Aspen | G40: CO | H40: 81611 | I40: 19023308 | J40: YMCR98701072871529
A41: AGENT00038 | B41: Harold Ward | C41: 1993-01-24 | D41: 171 Brickhill Circle | F41: Pooler | G41: GA | H41: 31322 | I41: 114283917 | J41: XFPA46888061021143
A42: AGENT00039 | B42: Jeremy Fields | C42: 2002-06-10 | D42: 2115 Longest Avenue | F42: Louisville | G42: KY | H42: 40204 | I42: 128039908 | J42: NFAG41955904385274
A43: AGENT00040 | B43: Michael Riley | C43: 2010-12-15 | D43: 224 Michael Sears Road | F43: Belchertown | G43: MA | H43: 1007 | I43: 77937915 | J43: BPIU33548981266102
A44: AGENT00041 | B44: John Tallman | C44: 2006-04-22 | D44: 2313 Mansfield Avenue | F44: Del City | G44: OK | H44: 73115 | I44: 38768204 | J44: YCPM81152663783872
A45: AGENT00042 | B45: Esther Ahmed | C45: 2010-02-27 | D45: 119 Redwood Road | F45: Manchester | G45: CT | H45: 6040 | I45: 88011435 | J45: ECWS51885965503134
A46: AGENT00043 | B46: Mary Norris | C46: 2011-08-07 | D46: 5073 West 65th Place | F46: Arvada | G46: CO | H46: 80003 | I46: 93553577 | J46: IDSZ07874822883626
A47: AGENT00044 | B47: Earnest White | C47: 2013-08-21 | D47: 7564 Moore Court | F47: Arvada | G47: CO | H47: 80005 | I47: 16618305 | J47: EHGZ29425971599083
A48: AGENT00045 | B48: Frances Melia | C48: 2001-03-09 | D48: 2139 Glynnwood Drive | F48: Savannah | G48: GA | H48: 31404 | I48: 50185849 | J48: SRTU89087626370729
A49: AGENT00046 | B49: William Ramos | C49: 2001-11-11 | D49: 22825 Paseo Place | F49: Hayward | G49: CA | H49: 94541 | I49: 74580381 | J49: XAYL42110131828573
A50: AGENT00047 | B50: Henry Arends | C50: 2009-06-13 | D50: 60 Bagley Street | F50: Saint Johnsbury | G50: VT | H50: 5819 | I50: 96611678 | J50: XWPZ93429840455468
... A58: AGENT00055 | B58: Wendi Hensley | C58: 1992-02-21 | D58: 7730 Wilkinson Road | F58: Nashville | G58: TN | H58: 37080 | I58: 72945591 | J58: FFJG64443961824050
A59: AGENT00056 | B59: Daniel Nance | C59: 2016-11-28 | D59: 2500 Medallion Drive | E59: #APT 148 | F59: Union City | G59: CA | H59: 94587 | I59: 87644793 | J59: ZTMC18946634687958
A60: AGENT00057 | B60: Debra Tripp | C60: 2011-03-12 | D60: 3194 Bladensburg Road Northeast | F60: Washington | G60: DC | H60: 20018 | I60: 89557833 | J60: QINB62773712676016
A61: AGENT00058 | B61: Nannie Thomas | C61: 1994-08-31 | D61: 827 10th Street Northeast | F61: Washington | G61: DC | H61: 20002 | I61: 14245602 | J61: EFRK76795304452686
A62: AGENT00059 | B62: Suzanne Amador | C62: 2008-12-14 | D62: 903 Burton Avenue | F62: Louisville | G62: KY | H62: 40208 | I62: 66731436 | J62: QTVE06059221536957
A63: AGENT00060 | B63: Vincent Rule | C63: 2000-12-21 | D63: 2502 Adrienne Way | F63: Louisville | G63: KY | H63: 40216 | I63: 127573193 | J63: NNQD57441399397776
A64: AGENT00061 | B64: Curtis Griffin | C64: 1994-07-29 | D64: 1780 142nd Avenue | F64: San Leandro | G64: CA | H64: 94578 | I64: 87748314 | J64: TGGO48192632068582
A65: AGENT00062 | B65: Diane Marburger | C65: 2012-08-24 | D65: 2001 Van Hoose Drive | F65: Fayetteville | G65: AR | H65: 72701 | I65: 25284568 | J65: WRNQ45980898120540
A66: AGENT00063 | B66: Leslie Lee | C66: 1998-10-17 | D66: 13525 West Stella Lane | F66: Litchfield Park | G66: AZ | H66: 85340 | I66: 92646029 | J66: OGPU80098723132854
A67: AGENT00064 | B67: James Evans | C67: 2003-05-29 | D67: 93 Marble Hill Road | F67: Waitsfield | G67: VT | H67: 5673 | I67: 99270087 | J67: ZEZK82145385865138
A68: AGENT00065 | B68: Elizabeth Curry | C68: 2009-08-17 | D68: 13066 North 56th Avenue | F68: Glendale | G68: AZ | H68: 85304 | I68: 104679007 | J68: KMRU23249802615601
A69: AGENT00066 | B69: Danielle Visvardis | C69: 2014-09-16 | D69: 35 Keach Avenue | F69: Worcester | G69: MA | H69: 1607 | I69: 101490043 | J69: OJKV85329684741331
A70: AGENT00067 | B70: Jonathan Smith | C70: 2003-08-09 | D70: 9401 3rd Street Road | F70: Louisville | G70: KY | H70: 40272 | I70: 26143747 | J70: NDPW31134564002955
A71: AGENT00068 | B71: Debra Ortega | C71: 2015-06-17 | D71: 61 Plymouth Lane | F71: Manchester | G71: CT | H71: 6040 | I71: 49124264 | J71: JDKI55297566920709
... A74: AGENT00071 | B74: Karen Olsen | C74: 2003-07-17 | D74: 649 Praderia Circle | F74: Fremont | G74: CA | H74: 94539 | I74: 21702837 | J74: UEZH74224396771892
A75: AGENT00072 | B75: Kate Mendes | C75: 1992-12-02 | D75: 100 Birney Street | E75: #A6 | F75: Peabody | G75: MA | H75: 1960 | I75: 26250698 | J75: QCWW55532754732879
A76: AGENT00073 | B76: Edgar Vazquez | C76: 2011-07-07 | D76: 4516 Old Seward Highway | F76: Anchorage | G76: AK | H76: 99503 | I76: 82636845 | J76: TKLO18911599752642
A77: AGENT00074 | B77: Claire Decinti | C77: 1999-04-22 | D77: 29 Vista Flores | F77: Pleasanton | G77: CA | H77: 94566 | I77: 58546503 | J77: UFJE04852683509089
A78: AGENT00075 | B78: Judy Kesselman | C78: 2001-02-10 | D78: 89 Plaistow Road | F78: Haverhill | G78: MA | H78: 1830 | I78: 30968662 | J78: QLXR90238004955533
A79: AGENT00076 | B79: Jason Dowling | C79: 1996-04-27 | D79: 235 Hugh Thomas Drive | F79: Panama City | G79: FL | H79: 32404 | I79: 72525526 | J79: OPHP95210778945160
A80: AGENT00077 | B80: Larry Sheley | C80: 1993-08-08 | D80: 313 Lone Oak Drive | F80: Norman | G80: OK | H80: 73071 | I80: 115478394 | J80: SOYF56326872937503
A81: AGENT00078 | B81: Shane Mclarty | C81: 2017-04-10 | D81: 369 Ruth Avenue | F81: Mountain View | G81: CA | H81: 94043 | I81: 59649865 | J81: SJAH52896250686985
A82: AGENT00079 | B82: Rivka Robinson | C82: 1997-12-11 | D82: 1008 Rhode Island Avenue Northwest | F82: Washington | G82: DC | H82: 20001 | I82: 119270857 | J82: SAHS72824131306931
A83: AGENT00080 | B83: Gary Simmons | C83: 2014-07-10 | D83: 11843 North 60th Avenue | F83: Glendale | G83: AZ | H83: 85304 | I83: 107838887 | J83: QHOY59291625073441
A84: AGENT00081 | B84: Frances Kocka | C84: 1995-07-02 | D84: 5244 West Port Au Prince Lane | F84: Glendale | G84: AZ | H84: 85306 | I84: 14258217 | J84: FVXO69898679507549
A85: AGENT00082 | B85: Bruce Rollins | C85: 2015-03-13 | D85: 1054 Overton Lea Road | F85: Nashville | G85: TN | H85: 37220 | I85: 78147791 | J85: BCPF23838135591983
A86: AGENT00083 | B86: Christopher Fontenot | C86: 1990-06-29 | D86: 9904 Daniel Drive | F86: Louisville | G86: KY | H86: 40118 | I86: 121752253 | J86: DHZC54326133627820
A87: AGENT00084 | B87: Brandon Fujii | C87: 2011-07-08 | D87: 4231 Laurel Street | E87: #APT 000101 | F87: Anchorage | G87: AK | H87: 99508 | I87: 45086238 | J87: NEEJ23567656975840
A88: AGENT00085 | B88: Suzanne Rutan | C88: 2000-12-19 | D88: 2237 Northwest 18th Street | F88: Oklahoma City | G88: OK | H88: 73107 | I88: 126639931 | J88: BQAF82775764630550
A89: AGENT00086 | B89: Shelia Morales | C89: 2002-04-22 | D89: 517 Wesley Avenue | F89: Nashville | G89: TN | H89: 37207 | I89: 36743849 | J89: UPBY22009074123142
A90: AGENT00087 | B90: Hazel Riegel | C90: 1998-11-27 | D90: 1265 Xavier Avenue | F90: Hayward | G90: CA | H90: 94545 | I90: 121086576 | J90: OGCK36406214425828
A91: AGENT00088 | B91: Sara Keith | C91: 2009-01-28 | D91: 29 Vista Flores | F91: Pleasanton | G91: CA | H91: 94566 | I91: 42301932 | J91: ADPI28499084429103
A92: AGENT00089 | B92: Jill Chreene | C92: 1996-02-20 | D92: 45 Baldridge Road | F92: Annapolis | G92: MD | H92: 21401 | I92: 108238677 | J92: ENOI80640229461509
A93: AGENT00090 | B93: Joshua Cherry | C93: 1990-11-22 | D93: 305 Brookside Court | F93: Manchester | G93: CT | H93: 6042 | I93: 91036517 | J93: DQEH00142970374186
A94: AGENT00091 | B94: Marie Driver | C94: 1998-04-27 | D94: 22825 Paseo Place | F94: Hayward | G94: CA | H94: 94541 | I94: 21835607 | J94: GPYT43428078920971
A95: AGENT00092 | B95: Gary Fernandez | C95: 2010-03-03 | D95: 802 East 37th Street | F95: Savannah | G95: GA | H95: 31401 | I95: 23000249 | J95: STSZ52823814965754
A96: AGENT00093 | B96: Christian Rau | C96: 2015-01-13 | D96: 5526 Thalman Drive | F96: Brentwood | G96: TN | H96: 37027 | I96: 52980550 | J96: PBOE57461807615642
A97: AGENT00094 | B97: Claudia Lennon | C97: 2013-04-29 | D97: 2008 Aberdeen Drive | F97: Crofton | G97: MD | H97: 21114 | I97: 21205075 | J97: WUGY06547890280364
A98: AGENT00095 | B98: Brenda Poston | C98: 2018-01-13 | D98: 138 Bolton Street | F98: Manchester | G98: CT | H98: 6040 | I98: 111511352 | J98: XDLC76847404990684
A99: AGENT00096 | B99: Terry Shaw | C99: 1990-07-03 | D99: 5650 West 60th Avenue | E99: A | F99: Arvada | G99: CO | H99: 80003 | I99: 121109136 | J99: VNZL86085621326610
A100: AGENT00097 | B100: Walter Wetzel | C100: 1999-05-01 | D100: 3546 Rosa L Parks Avenue | F100: Montgomery | G100: AL | H100: 36105 | I100: 28613851 | J100: SLNQ04446939633511
A101: AGENT00098 | B101: Fred Watson | C101: 1994-09-24 | D101: 9321 Amy Lane | F101: Panama City Beach | G101: FL | H101: 32407 | I101: 16097573 | J101: CZNF45094583427140
A102: AGENT00099 | B102: Sandra Hayashi | C102: 2003-01-31 | D102: 5157 West Kerry Lane | F102: Glendale | G102: AZ | H102: 85308 | I102: 127295730 | J102: YBDR91472107054002
A103: AGENT00100 | B103: Steve Hayes | C103: 2014-09-21 | D103: 12061 Johns Road | E103: #APT 000002 | F103: Anchorage | G103: AK | H103: 99515 | I103: 40708980 | J103: UDHO82054814895933
A104: AGENT00101 | B104: Gary Rogers | C104: 2000-07-21 | D104: 7650 West 68th Avenue | E104: #315 | F104: Arvada | G104: CO | H104: 80004 | I104: 52865141 | J104: XRRJ16577189083309
A105: AGENT00102 | B105: Mary Baker | C105: 1996-04-09 | D105: 4418 15th Street Northwest | F105: Washington | G105: DC | H105: 20011 | I105: 18048180 | J105: SPCS72717026359906
A106: AGENT00103 | B106: Jeffery Filgo | C106: 1995-07-06 | D106: 4113 Holiday Drive | F106: Panama City | G106: FL | H106: 32408 | I106: 89394041 | J106: HUII66210152910986
A107: AGENT00104 | B107: Howard Carter | C107: 1997-09-22 | D107: 20228 Crabtree Street | F107: Anchorage | G107: AK | H107: 99567 | I107: 28549608 | J107: KXZS94811967878848
A108: AGENT00105 | B108: Jonathan Labonte | C108: 1992-01-07 | D108: 6516 Nile Circle | F108: Arvada | G108: CO | H108: 80007 | I108: 34673762 | J108: DFEM16996667441685
A109: AGENT00106 | B109: Alice Burcham | C109: 1997-05-09 | D109: 1504 East 55th Street | F109: Savannah | G109: GA | H109: 31404 | I109: 20653084 | J109: LLNW82567313369027
A110: AGENT00107 | B110: Heather Miramontes | C110: 2000-09-11 | D110: 162 Wells Street | F110: Manchester | G110: CT | H110: 6040 | I110: 17120766 | J110: LMBX96096792073917
...

Sheet Vendors
A1: LOOKUP TABLE — Vendors (from vendor_data_2_.csv)
A3: VENDOR_ID | B3: VENDOR_NAME | C3: ADDRESS_LINE1 | D3: ADDRESS_LINE2 | E3: CITY | F3: STATE | G3: POSTAL_CODE
A4: VNDR00001 | B4: King, Proctor and Jones | C4: 2027 North Shannon Drive | D4: #5 | E4: Fayetteville | F4: AR | G4: 72703
A5: VNDR00002 | B5: Garcia Ltd | C5: 5701 East Shirley Lane | E5: Montgomery | F5: AL | G5: 36117
A6: VNDR00003 | B6: Cherry LLC | C6: 1217 Cottondale Road | E6: Montgomery | F6: AL | G6: 36109
A7: VNDR00004 | B7: Mays-Benson | C7: 227 West Montgomery Cross Road | D7: #736 | E7: Savannah | F7: GA | G7: 31406
A8: VNDR00005 | B8: Wilson PLC | C8: 23 North Hill Street | E8: Nashville | F8: TN | G8: 37210
A9: VNDR00006 | B9: Wallace Inc | C9: 6324 Moore Circle | E9: Arvada | F9: CO | G9: 80004
A10: VNDR00007 | B10: Alexander, Huynh and Hall | C10: 9 Thomas Street | E10: Ashland | F10: MA | G10: 1721
A11: VNDR00008 | B11: Young, Williams and Pope | C11: 1497 Greenbrier Road | E11: West Sacramento | F11: CA | G11: 95691
A12: VNDR00009 | B12: Flores, Haas and Fox | C12: 7912 Depew Street | E12: Arvada | F12: CO | G12: 80003
A13: VNDR00010 | B13: Mcclure Ltd | C13: 243 Kentucky Avenue | E13: Pasadena | F13: MD | G13: 21122
A14: VNDR00011 | B14: Morton LLC | C14: 218 Turtle Cove | E14: Panama City Beach | F14: FL | G14: 32413
A15: VNDR00012 | B15: Robertson, Perkins and Walton | C15: 5029 Montclair Drive | E15: Nashville | F15: TN | G15: 37211
A16: VNDR00013 | B16: Thomas Group | C16: 2269 Eastern Boulevard | E16: Montgomery | F16: AL | G16: 36117
A17: VNDR00014 | B17: Smith-Murphy | C17: 618 Ava Circle Northeast | E17: Washington | F17: DC | G17: 20017
A18: VNDR00015 | B18: Parker-Blake | C18: 3704 Hughes Road | E18: Louisville | F18: KY | G18: 40207
A19: VNDR00016 | B19: Navarro PLC | C19: 5856 Parfet Court | E19: Arvada | F19: CO | G19: 80004
... A21: VNDR00018 | B21: Bradley Ltd | C21: 4510 Eastern Avenue Northeast | E21: Washington | F21: DC | G21: 20018
A22: VNDR00019 | B22: Wells-Hooper | C22: 6521 North 65th Avenue | D22: #1D | E22: Glendale | F22: AZ | G22: 85301
A23: VNDR00020 | B23: Hamilton, Alexander and Wilkins | C23: 328 17th Street | E23: Paso Robles | F23: CA | G23: 93446
A24: VNDR00021 | B24: Willis, Griffin and Olsen | C24: 3373 Runnymede Place Northwest | E24: Washington | F24: DC | G24: 20015
A25: VNDR00022 | B25: Paul Group | C25: 18330 North 79th Avenue | D25: #3155 | E25: Glendale | F25: AZ | G25: 85308
A26: VNDR00023 | B26: Mckinney-Campbell | C26: 8219 Minor Lane | D26: #9 | E26: Louisville | F26: KY | G26: 40219
A27: VNDR00024 | B27: Rodriguez PLC | C27: 5556 West Northview Avenue | E27: Glendale | F27: AZ | G27: 85301
A28: VNDR00025 | B28: Wright Group | C28: 3231 North Kings Cross | E28: Fayetteville | F28: AR | G28: 72703
A29: VNDR00026 | B29: Bray PLC | C29: 736 Middle Turnpike East | E29: Manchester | F29: CT | G29: 6040
A30: VNDR00027 | B30: Bennett, Padilla and Williams | C30: 4024 Northwest 16th Street | E30: Oklahoma City | F30: OK | G30: 73107
A31: VNDR00028 | B31: Hawkins, Hernandez and Carter | C31: 38676 Greenwich Circle | E31: Fremont | F31: CA | G31: 94536
A32: VNDR00029 | B32: Grant-Carter | C32: 4439 Gale Street | E32: Livermore | F32: CA | G32: 94550
A33: VNDR00030 | B33: Smith Inc | C33: 38 Renwick Road | E33: Melrose | F33: MA | G33: 2176
A34: VNDR00031 | B34: Johnson Ltd | C34: 2619 North Quality Lane | D34: #315 | E34: Fayetteville | F34: AR | G34: 72703
A35: VNDR00032 | B35: Horne, Hinton and Lee | C35: 1516 Ringe Drive | E35: Severn | F35: MD | G35: 21144
A36: VNDR00033 | B36: Hooper-Garrett | C36: 1522 South 36th Street | E36: Louisville | F36: KY | G36: 40211
A37: VNDR00034 | B37: Davis and Sons | C37: 1079 East Kentucky Street | E37: Louisville | F37: KY | G37: 40204
A38: VNDR00035 | B38: Dixon Group | C38: 841 Whittier Hill Road | F38: VT | G38: 5647
A39: VNDR00036 | B39: Bryant, Murray and Lee | C39: 4075 North Cadillac Drive | D39: #2 | E39: Fayetteville | F39: AR | G39: 72703
A40: VNDR00037 | B40: Schmitt-Johnson | C40: 3901 Old Seward Highway | D40: #STE 000016 | E40: Anchorage | F40: AK | G40: 99503
A41: VNDR00038 | B41: Hoover and Sons | C41: 1430 South Gay Avenue | E41: Panama City | F41: FL | G41: 32404
A42: VNDR00039 | B42: Thomas and Sons | C42: 85 West Seymeria Drive | E42: Beverly Hills | F42: FL | G42: 34465
A43: VNDR00040 | B43: Reynolds-Tucker | C43: 46 Lilac Street | E43: Manchester | F43: CT | G43: 6040
A44: VNDR00041 | B44: Miller-Hall | C44: 8569 Vermont 9 | E44: Woodford | F44: VT | G44: 5201
A45: VNDR00042 | B45: Armstrong-Summers | C45: 2 Addison Place | E45: Bloomingdale | F45: GA | G45: 31302
A46: VNDR00043 | B46: Poole Ltd | C46: 20097 Butterfield Drive | E46: Castro Valley | F46: CA | G46: 94546
A47: VNDR00044 | B47: Garza, Giles and Palmer | C47: 7509 Linda Lane | E47: Panama City | F47: FL | G47: 32404
A48: VNDR00045 | B48: Bell PLC | C48: 17480 Beaujolais Circle | E48: Anchorage | F48: AK | G48: 99577
A49: VNDR00046 | B49: Anderson Inc | C49: 324 East Drive | E49: Montgomery | F49: AL | G49: 36113
A50: VNDR00047 | B50: Solis-Morales | C50: 1407 Walden Court | E50: Crofton | F50: MD | G50: 21114
A51: VNDR00048 | B51: Cooke, Wallace and Perry | C51: 5801 South Watterson Trail | E51: Louisville | F51: KY | G51: 40291
A52: VNDR00049 | B52: Rose Ltd | C52: 1123 Glenwood Avenue | E52: Nashville | F52: TN | G52: 37204
A53: VNDR00050 | B53: Rivera, Johnson and Drake | C53: 243 New State Road | D53: A-D | E53: Manchester | F53: CT | G53: 6042
A54: VNDR00051 | B54: Roberts-Garcia | C54: 6624 Strawberry Lane | E54: Louisville | F54: KY | G54: 40214
A55: VNDR00052 | B55: Garcia-Brown | C55: 124 Rod Key Street | E55: Lyndon | F55: VT | G55: 5851
A56: VNDR00053 | B56: Kelly-Mosley | C56: 441 Merritt Avenue | E56: Oakland | F56: CA | G56: 94610
A57: VNDR00054 | B57: Brown, Johnston and Anderson | C57: 1 Portsmouth Road | E57: Piedmont | F57: CA | G57: 94610
A58: VNDR00055 | B58: Morris, Patton and Rodriguez | C58: 8521 Crystal Street | E58: Anchorage | F58: AK | G58: 99502
A59: VNDR00056 | B59: Russell, Mills and Calderon | C59: 1823 Dinger Road | E59: Annapolis | F59: MD | G59: 21402
A60: VNDR00057 | B60: Mckinney-Riley | C60: 1010 10th Street Northeast | E60: Washington | F60: DC | G60: 20002
A61: VNDR00058 | B61: Estrada PLC | C61: 3 Mad Anthony Lane | E61: Savannah | F61: GA | G61: 31411
A62: VNDR00059 | B62: Long, Cooper and Vance | C62: 16502 South Main Street | D62: #5 | E62: Gardena | F62: CA | G62: 90248
A63: VNDR00060 | B63: Taylor, Holt and Stout | C63: 19 Heritage | E63: Oakland | F63: CA | G63: 94605
A64: VNDR00061 | B64: Green Ltd | C64: 165 Quincy Shore Drive | D64: #C27 | E64: Quincy | F64: MA | G64: 2171
A65: VNDR00062 | B65: Ramos Ltd | C65: 7728 Twin Oaks Road | E65: Severn | F65: MD | G65: 21144
A66: VNDR00063 | B66: Lowe-Wilson | C66: 5630 Silverado Way | D66: #STE A8 | E66: Anchorage | F66: AK | G66: 99518
A67: VNDR00064 | B67: Hill Ltd | C67: 712 Southwest 1st Street | E67: Moore | F67: OK | G67: 73160
A68: VNDR00065 | B68: Whitehead-Roberson | C68: 6624 Strawberry Lane | E68: Louisville | F68: KY | G68: 40214
A69: VNDR00066 | B69: Hart-Carpenter | C69: 266 South J Street | E69: Livermore | F69: CA | G69: 94550
A70: VNDR00067 | B70: Weaver-Ellis | C70: 8820 Culebra Street | E70: Arvada | F70: CO | G70: 80007
A71: VNDR00068 | B71: Moore Group | C71: 13583 West 68th Avenue | E71: Arvada | F71: CO | G71: 80004
A72: VNDR00069 | B72: Escobar, Fields and Moran | C72: 1015 Castle Road | E72: Edmond | F72: OK | G72: 73034
A73: VNDR00070 | B73: Graves and Sons | C73: 219 Bidwell Street | E73: Manchester | F73: CT | G73: 6040
A74: VNDR00071 | B74: Martinez-Thomas | C74: 3203 US Highway 98 | D74: A | E74: Mexico Beach | F74: FL | G74: 32456
A75: VNDR00072 | B75: Thompson-Wilson | C75: 7711 North 51st Avenue | D75: #1180 | E75: Glendale | F75: AZ | G75: 85301
A76: VNDR00073 | B76: Griffin-Shaw | C76: 125 Summer Street | E76: Manchester | F76: CT | G76: 6040
A77: VNDR00074 | B77: Fox-Anderson | C77: 169 Avenida Drive | D77: M | E77: Berkeley | F77: CA | G77: 94708
A78: VNDR00075 | B78: Blackwell-Foster | C78: 3609 Meadow Drive | E78: Nashville | F78: TN | G78: 37215
A79: VNDR00076 | B79: Schaefer, Paul and Ayala | C79: 4300 Kansas Avenue Northwest | E79: Washington | F79: DC | G79: 20011
A80: VNDR00077 | B80: Bartlett-Winters | C80: 113 Dove Lane | E80: Savannah | F80: GA | G80: 31406
A81: VNDR00078 | B81: Young Ltd | C81: 835 Shiloh Court | E81: Redding | F81: CA | G81: 96003
A82: VNDR00079 | B82: Lopez-Wilson | C82: 809 Blue Ridge Drive | E82: Edmond | F82: OK | G82: 73003
A83: VNDR00080 | B83: Cooper Ltd | C83: 595 West 15th Street | E83: Fayetteville | F83: AR | G83: 72701
A84: VNDR00081 | B84: Perez-Richards | C84: 8704 Bayberry Place | E84: Plantation | F84: KY | G84: 40242
A85: VNDR00082 | B85: Barnes PLC | C85: 2409 Park Street | E85: Selma | F85: CA | G85: 93662
A86: VNDR00083 | B86: Kennedy, Benjamin and Young | C86: 1217 Cottondale Road | E86: Montgomery | F86: AL | G86: 36109
A87: VNDR00084 | B87: Smith-Schwartz | C87: 1520 H Street Northwest | E87: Washington | F87: DC | G87: 20006
A88: VNDR00085 | B88: Pratt, Jenkins and Willis | C88: 400 D Street | D88: #STE 1B | E88: Anchorage | F88: AK | G88: 99501
A89: VNDR00086 | B89: Guerrero, Norman and Baker | C89: 55 Russells Mills Road | E89: Dartmouth | F89: MA | G89: 2748
A90: VNDR00087 | B90: Davis PLC | C90: 2130 Loren Circle | E90: Fayetteville | F90: AR | G90: 72701
A91: VNDR00088 | B91: Richards, Yates and Rich | C91: 8726 Downey Road | E91: Severn | F91: MD | G91: 21144
A92: VNDR00089 | B92: Miller-Schmidt | C92: 119 Redwood Road | E92: Manchester | F92: CT | G92: 6040
A93: VNDR00090 | B93: Harris-Joyce | C93: 2222 Martin Luther King Junior Boulevard | E93: Fayetteville | F93: AR | G93: 72701
A94: VNDR00091 | B94: Hatfield, Jones and Jensen | C94: 2A Cleveland Park Rd | E94: Freetown | F94: MA | G94: 2717
A95: VNDR00092 | B95: Knapp-Thornton | C95: 625 West Main Street | E95: Moore | F95: OK | G95: 73160
A96: VNDR00093 | B96: Mullins-Ramsey | C96: 1345 G Street Southeast | E96: Washington | F96: DC | G96: 20003
A97: VNDR00094 | B97: Payne-Smith | C97: 334 North Cove Boulevard | E97: Panama City | F97: FL | G97: 32401
A98: VNDR00095 | B98: Ramsey Group | C98: 4331 Foeburn Lane | E98: Louisville | F98: KY | G98: 40207
A99: VNDR00096 | B99: Villanueva Ltd | C99: 7256 West 84th Way | D99: #918 | E99: Arvada | F99: CO | G99: 80003
A100: VNDR00097 | B100: Mitchell, Jackson and Norris | C100: 2315 Kezey Court | E100: Crofton | F100: MD | G100: 21114
A101: VNDR00098 | B101: Rodriguez Inc | C101: 1641 Kramer Street Northeast | E101: Washington | F101: DC | G101: 20002
A102: VNDR00099 | B102: Welch, Keller and Hicks | C102: 1820 22nd Street Southeast | E102: Washington | F102: DC | G102: 20020
...
